{"inkVersion":21,"root":[["#","^title: The Assassins Arc","/#","#","^author: Emely T.","/#",{"->":"gedeonAppears"},["done",{"#f":5,"#n":"g-0"}],null],"done",{"gedeonAppears":[["^Gedeon appears.","\n","^<em>\"Greetingsssss sssssly one.\"</em>","\n",["ev",{"^->":"gedeonAppears.0.4.$r1"},{"temp=":"$r"},"str",{"->":".^.s"},[{"#n":"$r1"}],"/str","/ev",{"*":".^.^.c-0","flg":2},{"s":["^Hello",{"->":"$r","var":true},null]}],{"c-0":["ev",{"^->":"gedeonAppears.0.c-0.$r2"},"/ev",{"temp=":"$r"},{"->":".^.^.4.s"},[{"#n":"$r2"}],"\n",{"->":".^.^.^.weHaveBeenObssss"},{"#f":5}]}],{"weHaveBeenObssss":[["^<em>\"We have been obssssserving you.\"</em>","\n",["ev",{"^->":"gedeonAppears.weHaveBeenObssss.0.2.$r1"},{"temp=":"$r"},"str",{"->":".^.s"},[{"#n":"$r1"}],"/str","/ev",{"*":".^.^.c-0","flg":2},{"s":["^So?",{"->":"$r","var":true},null]}],{"c-0":["ev",{"^->":"gedeonAppears.weHaveBeenObssss.0.c-0.$r2"},"/ev",{"temp=":"$r"},{"->":".^.^.2.s"},[{"#n":"$r2"}],"\n",{"->":".^.^.^.^.sssssoWeWantToAs"},{"#f":5}]}],{"#f":1}],"sssssoWeWantToAs":[["^<em>\"Ssssso, we want to asssssissssst you.\"</em>","\n",["ev",{"^->":"gedeonAppears.sssssoWeWantToAs.0.2.$r1"},{"temp=":"$r"},"str",{"->":".^.s"},[{"#n":"$r1"}],"/str","/ev",{"*":".^.^.c-0","flg":2},{"s":["^How?",{"->":"$r","var":true},null]}],{"c-0":["ev",{"^->":"gedeonAppears.sssssoWeWantToAs.0.c-0.$r2"},"/ev",{"temp=":"$r"},{"->":".^.^.2.s"},[{"#n":"$r2"}],"\n",{"->":".^.^.^.^.doYouDreamOfRich"},{"#f":5}]}],{"#f":1}],"doYouDreamOfRich":[["^<em>\"Do you dream of richesssss?\"</em>","\n",["ev",{"^->":"gedeonAppears.doYouDreamOfRich.0.2.$r1"},{"temp=":"$r"},"str",{"->":".^.s"},[{"#n":"$r1"}],"/str","/ev",{"*":".^.^.c-0","flg":2},{"s":["^Yes",{"->":"$r","var":true},null]}],["ev",{"^->":"gedeonAppears.doYouDreamOfRich.0.3.$r1"},{"temp=":"$r"},"str",{"->":".^.s"},[{"#n":"$r1"}],"/str","/ev",{"*":".^.^.c-1","flg":2},{"s":["^No",{"->":"$r","var":true},null]}],{"c-0":["ev",{"^->":"gedeonAppears.doYouDreamOfRich.0.c-0.$r2"},"/ev",{"temp=":"$r"},{"->":".^.^.2.s"},[{"#n":"$r2"}],"\n",{"->":".^.^.^.^.weCanGrantYouSss"},{"#f":5}],"c-1":["ev",{"^->":"gedeonAppears.doYouDreamOfRich.0.c-1.$r2"},"/ev",{"temp=":"$r"},{"->":".^.^.3.s"},[{"#n":"$r2"}],"\n",{"->":".^.^.^.^.ahSssssoWeAreThe"},{"#f":5}]}],{"#f":1}],"weCanGrantYouSss":[["^<em>\"We can grant you sssssaid wish.\"</em>","\n",["ev",{"^->":"gedeonAppears.weCanGrantYouSss.0.2.$r1"},{"temp=":"$r"},"str",{"->":".^.s"},[{"#n":"$r1"}],"/str","/ev",{"*":".^.^.c-0","flg":2},{"s":["^Next",{"->":"$r","var":true},null]}],{"c-0":["ev",{"^->":"gedeonAppears.weCanGrantYouSss.0.c-0.$r2"},"/ev",{"temp=":"$r"},{"->":".^.^.2.s"},[{"#n":"$r2"}],"\n",{"->":".^.^.^.^.allYouMussssstDo"},{"#f":5}]}],{"#f":1}],"ahSssssoWeAreThe":[["^<em>\"Ah, ssssso we are the sssssame.\"</em>","\n",["ev",{"^->":"gedeonAppears.ahSssssoWeAreThe.0.2.$r1"},{"temp=":"$r"},"str",{"->":".^.s"},[{"#n":"$r1"}],"/str","/ev",{"*":".^.^.c-0","flg":2},{"s":["^Next",{"->":"$r","var":true},null]}],{"c-0":["ev",{"^->":"gedeonAppears.ahSssssoWeAreThe.0.c-0.$r2"},"/ev",{"temp=":"$r"},{"->":".^.^.2.s"},[{"#n":"$r2"}],"\n",{"->":".^.^.^.^.wePlaccccceImpor"},{"#f":5}]}],{"#f":1}],"allYouMussssstDo":[["^<em>\"All you mussssst do isssss sssssimple.\"</em>","\n",["ev",{"^->":"gedeonAppears.allYouMussssstDo.0.2.$r1"},{"temp=":"$r"},"str",{"->":".^.s"},[{"#n":"$r1"}],"/str","/ev",{"*":".^.^.c-0","flg":2},{"s":["^Next",{"->":"$r","var":true},null]}],{"c-0":["ev",{"^->":"gedeonAppears.allYouMussssstDo.0.c-0.$r2"},"/ev",{"temp=":"$r"},{"->":".^.^.2.s"},[{"#n":"$r2"}],"\n",{"->":".^.^.^.^.pledgeYourLoyalt"},{"#f":5}]}],{"#f":1}],"wePlaccccceImpor":[["^<em>\"We placcccce importanccccce on more valuable mattersssss.\"</em>","\n",["ev",{"^->":"gedeonAppears.wePlaccccceImpor.0.2.$r1"},{"temp=":"$r"},"str",{"->":".^.s"},[{"#n":"$r1"}],"/str","/ev",{"*":".^.^.c-0","flg":2},{"s":["^Next",{"->":"$r","var":true},null]}],{"c-0":["ev",{"^->":"gedeonAppears.wePlaccccceImpor.0.c-0.$r2"},"/ev",{"temp=":"$r"},{"->":".^.^.2.s"},[{"#n":"$r2"}],"\n",{"->":".^.^.^.^.suchAsssss"},{"#f":5}]}],{"#f":1}],"pledgeYourLoyalt":[["^<em>\"Pledge your loyalty and allegianccccce to usssss.\" </em>","\n",["ev",{"^->":"gedeonAppears.pledgeYourLoyalt.0.2.$r1"},{"temp=":"$r"},"str",{"->":".^.s"},[{"#n":"$r1"}],"/str","/ev",{"*":".^.^.c-0","flg":2},{"s":["^Next",{"->":"$r","var":true},null]}],{"c-0":["ev",{"^->":"gedeonAppears.pledgeYourLoyalt.0.c-0.$r2"},"/ev",{"temp=":"$r"},{"->":".^.^.2.s"},[{"#n":"$r2"}],"\n",{"->":".^.^.^.^.iAndAllYouDessss"},{"#f":5}]}],{"#f":1}],"suchAsssss":[["^<em>\"Such asssss...\"</em>","\n",["ev",{"^->":"gedeonAppears.suchAsssss.0.2.$r1"},{"temp=":"$r"},"str",{"->":".^.s"},[{"#n":"$r1"}],"/str","/ev",{"*":".^.^.c-0","flg":2},{"s":["^Next",{"->":"$r","var":true},null]}],{"c-0":["ev",{"^->":"gedeonAppears.suchAsssss.0.c-0.$r2"},"/ev",{"temp=":"$r"},{"->":".^.^.2.s"},[{"#n":"$r2"}],"\n",{"->":".^.^.^.^.loyalty"},{"#f":5}]}],{"#f":1}],"iAndAllYouDessss":[["^<i>\"And all you desssssire will become reality.\"</i>","\n",["ev",{"^->":"gedeonAppears.iAndAllYouDessss.0.2.$r1"},{"temp=":"$r"},"str",{"->":".^.s"},[{"#n":"$r1"}],"/str","/ev",{"*":".^.^.c-0","flg":2},{"s":["^I pledge",{"->":"$r","var":true},null]}],["ev",{"^->":"gedeonAppears.iAndAllYouDessss.0.3.$r1"},{"temp=":"$r"},"str",{"->":".^.s"},[{"#n":"$r1"}],"/str","/ev",{"*":".^.^.c-1","flg":2},{"s":["^Thanks, but no thanksssss",{"->":"$r","var":true},null]}],{"c-0":["ev",{"^->":"gedeonAppears.iAndAllYouDessss.0.c-0.$r2"},"/ev",{"temp=":"$r"},{"->":".^.^.2.s"},[{"#n":"$r2"}],"\n",{"->":".^.^.^.^.fantassssstic"},{"#f":5}],"c-1":["ev",{"^->":"gedeonAppears.iAndAllYouDessss.0.c-1.$r2"},"/ev",{"temp=":"$r"},{"->":".^.^.3.s"},[{"#n":"$r2"}],"\n",{"->":".^.^.^.^.gedeonLooksAngry"},{"#f":5}]}],{"#f":1}],"loyalty":[["^<em>\"loyalty...\"</em>","\n",["ev",{"^->":"gedeonAppears.loyalty.0.2.$r1"},{"temp=":"$r"},"str",{"->":".^.s"},[{"#n":"$r1"}],"/str","/ev",{"*":".^.^.c-0","flg":2},{"s":["^Next",{"->":"$r","var":true},null]}],{"c-0":["ev",{"^->":"gedeonAppears.loyalty.0.c-0.$r2"},"/ev",{"temp=":"$r"},{"->":".^.^.2.s"},[{"#n":"$r2"}],"\n",{"->":".^.^.^.^.wouldYouNotAgree"},{"#f":5}]}],{"#f":1}],"fantassssstic":[["^<em>\"Fantassssstic.\"</em>","\n",["ev",{"^->":"gedeonAppears.fantassssstic.0.2.$r1"},{"temp=":"$r"},"str",{"->":".^.s"},[{"#n":"$r1"}],"/str","/ev",{"*":".^.^.c-0","flg":2},{"s":["^Next",{"->":"$r","var":true},null]}],{"c-0":["ev",{"^->":"gedeonAppears.fantassssstic.0.c-0.$r2"},"/ev",{"temp=":"$r"},{"->":".^.^.2.s"},[{"#n":"$r2"}],"\n",{"->":".^.^.^.^.nowYouMussssstPa"},{"#f":5}]}],{"#f":1}],"wouldYouNotAgree":[["^<em>\"Would you not agree?\"</em>","\n",["ev",{"^->":"gedeonAppears.wouldYouNotAgree.0.2.$r1"},{"temp=":"$r"},"str",{"->":".^.s"},[{"#n":"$r1"}],"/str","/ev",{"*":".^.^.c-0","flg":2},{"s":["^I would",{"->":"$r","var":true},null]}],["ev",{"^->":"gedeonAppears.wouldYouNotAgree.0.3.$r1"},{"temp=":"$r"},"str",{"->":".^.s"},[{"#n":"$r1"}],"/str","/ev",{"*":".^.^.c-1","flg":2},{"s":["^No, not really",{"->":"$r","var":true},null]}],["ev",{"^->":"gedeonAppears.wouldYouNotAgree.0.4.$r1"},{"temp=":"$r"},"str",{"->":".^.s"},[{"#n":"$r1"}],"/str","/ev",{"*":".^.^.c-2","flg":2},{"s":["^Why loyalty, when I can have money",{"->":"$r","var":true},null]}],{"c-0":["ev",{"^->":"gedeonAppears.wouldYouNotAgree.0.c-0.$r2"},"/ev",{"temp=":"$r"},{"->":".^.^.2.s"},[{"#n":"$r2"}],"\n",{"->":".^.^.^.^.excccccellent"},{"#f":5}],"c-1":["ev",{"^->":"gedeonAppears.wouldYouNotAgree.0.c-1.$r2"},"/ev",{"temp=":"$r"},{"->":".^.^.3.s"},[{"#n":"$r2"}],"\n",{"->":".^.^.^.^.hmmmmm"},{"#f":5}],"c-2":["ev",{"^->":"gedeonAppears.wouldYouNotAgree.0.c-2.$r2"},"/ev",{"temp=":"$r"},{"->":".^.^.4.s"},[{"#n":"$r2"}],"\n",{"->":".^.^.^.^.punctuatedStitch"},{"#f":5}]}],{"#f":1}],"gedeonLooksAngry":[["^Gedeon looks angry.<em></em>","\n","^<i>\"You dare mock usssss?!\"</i>","\n",["ev",{"^->":"gedeonAppears.gedeonLooksAngry.0.4.$r1"},{"temp=":"$r"},"str",{"->":".^.s"},[{"#n":"$r1"}],"/str","/ev",{"*":".^.^.c-0","flg":2},{"s":["^Yesssss",{"->":"$r","var":true},null]}],["ev",{"^->":"gedeonAppears.gedeonLooksAngry.0.5.$r1"},{"temp=":"$r"},"str",{"->":".^.s"},[{"#n":"$r1"}],"/str","/ev",{"*":".^.^.c-1","flg":2},{"s":["^No, I pledge",{"->":"$r","var":true},null]}],{"c-0":["ev",{"^->":"gedeonAppears.gedeonLooksAngry.0.c-0.$r2"},"/ev",{"temp=":"$r"},{"->":".^.^.4.s"},[{"#n":"$r2"}],"\n",{"->":".^.^.^.^.itSsssseemsssssW"},{"#f":5}],"c-1":["ev",{"^->":"gedeonAppears.gedeonLooksAngry.0.c-1.$r2"},"/ev",{"temp=":"$r"},{"->":".^.^.5.s"},[{"#n":"$r2"}],"\n",{"->":".^.^.^.^.good"},{"#f":5}]}],{"#f":1}],"nowYouMussssstPa":[["^<em>\"Now, you mussssst passsss a tessssst.\"</em>","\n",["ev",{"^->":"gedeonAppears.nowYouMussssstPa.0.2.$r1"},{"temp=":"$r"},"str",{"->":".^.s"},[{"#n":"$r1"}],"/str","/ev",{"*":".^.^.c-0","flg":2},{"s":["^What test?",{"->":"$r","var":true},null]}],["ev",{"^->":"gedeonAppears.nowYouMussssstPa.0.3.$r1"},{"temp=":"$r"},"str",{"->":".^.s"},[{"#n":"$r1"}],"/str","/ev",{"*":".^.^.c-1","flg":2},{"s":["^Nevermind",{"->":"$r","var":true},null]}],{"c-0":["ev",{"^->":"gedeonAppears.nowYouMussssstPa.0.c-0.$r2"},"/ev",{"temp=":"$r"},{"->":".^.^.2.s"},[{"#n":"$r2"}],"\n",{"->":".^.^.^.^.weRequireYourSss"},{"#f":5}],"c-1":["ev",{"^->":"gedeonAppears.nowYouMussssstPa.0.c-1.$r2"},"/ev",{"temp=":"$r"},{"->":".^.^.3.s"},[{"#n":"$r2"}],"\n",{"->":".^.^.^.^.no"},{"#f":5}]}],{"#f":1}],"excccccellent":[["^<em>\"Excccccellent\"</em>","\n",["ev",{"^->":"gedeonAppears.excccccellent.0.2.$r1"},{"temp=":"$r"},"str",{"->":".^.s"},[{"#n":"$r1"}],"/str","/ev",{"*":".^.^.c-0","flg":2},{"s":["^Next",{"->":"$r","var":true},null]}],{"c-0":["ev",{"^->":"gedeonAppears.excccccellent.0.c-0.$r2"},"/ev",{"temp=":"$r"},{"->":".^.^.2.s"},[{"#n":"$r2"}],"\n",{"->":".^.^.^.^.pledgeYourAllegi"},{"#f":5}]}],{"#f":1}],"hmmmmm":[["^<em>\"Hmmmmm\"</em>","\n",["ev",{"^->":"gedeonAppears.hmmmmm.0.2.$r1"},{"temp=":"$r"},"str",{"->":".^.s"},[{"#n":"$r1"}],"/str","/ev",{"*":".^.^.c-0","flg":2},{"s":["^Next",{"->":"$r","var":true},null]}],{"c-0":["ev",{"^->":"gedeonAppears.hmmmmm.0.c-0.$r2"},"/ev",{"temp=":"$r"},{"->":".^.^.2.s"},[{"#n":"$r2"}],"\n",{"->":".^.^.^.^.thenPerhapsssss"},{"#f":5}]}],{"#f":1}],"punctuatedStitch":[["^<em>\"....\"</em>","\n",["ev",{"^->":"gedeonAppears.punctuatedStitch.0.2.$r1"},{"temp=":"$r"},"str",{"->":".^.s"},[{"#n":"$r1"}],"/str","/ev",{"*":".^.^.c-0","flg":2},{"s":["^Next",{"->":"$r","var":true},null]}],{"c-0":["ev",{"^->":"gedeonAppears.punctuatedStitch.0.c-0.$r2"},"/ev",{"temp=":"$r"},{"->":".^.^.2.s"},[{"#n":"$r2"}],"\n",{"->":".^.^.^.^.well"},{"#f":5}]}],{"#f":1}],"itSsssseemsssssW":[["^<em>\"It ssssseemsssss we were wrong about you after all.\" </em>","\n",["ev",{"^->":"gedeonAppears.itSsssseemsssssW.0.2.$r1"},{"temp=":"$r"},"str",{"->":".^.s"},[{"#n":"$r1"}],"/str","/ev",{"*":".^.^.c-0","flg":2},{"s":["^Next",{"->":"$r","var":true},null]}],{"c-0":["ev",{"^->":"gedeonAppears.itSsssseemsssssW.0.c-0.$r2"},"/ev",{"temp=":"$r"},{"->":".^.^.2.s"},[{"#n":"$r2"}],"\n",{"->":".^.^.^.^.iHowDisssssappoi"},{"#f":5}]}],{"#f":1}],"good":[["^<em>\"Good.\"</em>","\n",["ev",{"^->":"gedeonAppears.good.0.2.$r1"},{"temp=":"$r"},"str",{"->":".^.s"},[{"#n":"$r1"}],"/str","/ev",{"*":".^.^.c-0","flg":2},{"s":["^Next",{"->":"$r","var":true},null]}],{"c-0":["ev",{"^->":"gedeonAppears.good.0.c-0.$r2"},"/ev",{"temp=":"$r"},{"->":".^.^.2.s"},[{"#n":"$r2"}],"\n",{"->":".^.^.^.^.nowYouMussssstPa"},{"#f":5}]}],{"#f":1}],"weRequireYourSss":[["^<em>\"We require your ssssstrongest poissssson for tesssssting.\"</em>","\n",["ev",{"^->":"gedeonAppears.weRequireYourSss.0.2.$r1"},{"temp=":"$r"},"str",{"->":".^.s"},[{"#n":"$r1"}],"/str","/ev",{"*":".^.^.c-0","flg":2},{"s":["^Death Potion",{"->":"$r","var":true},null]}],["ev",{"^->":"gedeonAppears.weRequireYourSss.0.3.$r1"},{"temp=":"$r"},"str",{"->":".^.s"},[{"#n":"$r1"}],"/str","/ev",{"*":".^.^.c-1","flg":2},{"s":["^Non-death Potion",{"->":"$r","var":true},null]}],{"c-0":["ev",{"^->":"gedeonAppears.weRequireYourSss.0.c-0.$r2"},"/ev",{"temp=":"$r"},{"->":".^.^.2.s"},[{"#n":"$r2"}],"\n",{"->":".^.^.^.^.excccccellent1"},{"#f":5}],"c-1":["ev",{"^->":"gedeonAppears.weRequireYourSss.0.c-1.$r2"},"/ev",{"temp=":"$r"},{"->":".^.^.3.s"},[{"#n":"$r2"}],"\n",{"->":".^.^.^.^.hmmmmm1"},{"#f":5}]}],{"#f":1}],"no":[["^<em>\"No\"</em>","\n",["ev",{"^->":"gedeonAppears.no.0.2.$r1"},{"temp=":"$r"},"str",{"->":".^.s"},[{"#n":"$r1"}],"/str","/ev",{"*":".^.^.c-0","flg":2},{"s":["^Next",{"->":"$r","var":true},null]}],{"c-0":["ev",{"^->":"gedeonAppears.no.0.c-0.$r2"},"/ev",{"temp=":"$r"},{"->":".^.^.2.s"},[{"#n":"$r2"}],"\n",{"->":".^.^.^.^.youMussssst"},{"#f":5}]}],{"#f":1}],"pledgeYourAllegi":[["^<em>\"Pledge your allegianccccce to the most loyal of guildsssss.\"</em>","\n",["ev",{"^->":"gedeonAppears.pledgeYourAllegi.0.2.$r1"},{"temp=":"$r"},"str",{"->":".^.s"},[{"#n":"$r1"}],"/str","/ev",{"*":".^.^.c-0","flg":2},{"s":["^I Pledge",{"->":"$r","var":true},null]}],["ev",{"^->":"gedeonAppears.pledgeYourAllegi.0.3.$r1"},{"temp=":"$r"},"str",{"->":".^.s"},[{"#n":"$r1"}],"/str","/ev",{"*":".^.^.c-1","flg":2},{"s":["^Nahh, I don't wanna",{"->":"$r","var":true},null]}],{"c-0":["ev",{"^->":"gedeonAppears.pledgeYourAllegi.0.c-0.$r2"},"/ev",{"temp=":"$r"},{"->":".^.^.2.s"},[{"#n":"$r2"}],"\n",{"->":".^.^.^.^.fantassssstic"},{"#f":5}],"c-1":["ev",{"^->":"gedeonAppears.pledgeYourAllegi.0.c-1.$r2"},"/ev",{"temp=":"$r"},{"->":".^.^.3.s"},[{"#n":"$r2"}],"\n",{"->":".^.^.^.^.gedeonLooksAngry1"},{"#f":5}]}],{"#f":1}],"thenPerhapsssss":[["^<em>\"Then perhapsssss...\"</em>","\n",["ev",{"^->":"gedeonAppears.thenPerhapsssss.0.2.$r1"},{"temp=":"$r"},"str",{"->":".^.s"},[{"#n":"$r1"}],"/str","/ev",{"*":".^.^.c-0","flg":2},{"s":["^Next",{"->":"$r","var":true},null]}],{"c-0":["ev",{"^->":"gedeonAppears.thenPerhapsssss.0.c-0.$r2"},"/ev",{"temp=":"$r"},{"->":".^.^.2.s"},[{"#n":"$r2"}],"\n",{"->":".^.^.^.^.weDifferFarGreat"},{"#f":5}]}],{"#f":1}],"well":[["^<em>\"Well...\"</em>","\n",["ev",{"^->":"gedeonAppears.well.0.2.$r1"},{"temp=":"$r"},"str",{"->":".^.s"},[{"#n":"$r1"}],"/str","/ev",{"*":".^.^.c-0","flg":2},{"s":["^Next",{"->":"$r","var":true},null]}],{"c-0":["ev",{"^->":"gedeonAppears.well.0.c-0.$r2"},"/ev",{"temp=":"$r"},{"->":".^.^.2.s"},[{"#n":"$r2"}],"\n",{"->":".^.^.^.^.weCanGrantYouSss"},{"#f":5}]}],{"#f":1}],"iHowDisssssappoi":["^<i>\"How disssssappointing.\"</i>","\n","^Gedeon leaves.","\n","^<strong>Defaults to Normal Arc.</strong>","\n","end",{"#f":1}],"excccccellent1":[["^<em>\"Excccccellent\"</em>","\n","^Gedeon leaves.<em></em>","\n",["ev",{"^->":"gedeonAppears.excccccellent1.0.4.$r1"},{"temp=":"$r"},"str",{"->":".^.s"},[{"#n":"$r1"}],"/str","/ev",{"*":".^.^.c-0","flg":2},{"s":["^Next",{"->":"$r","var":true},null]}],{"c-0":["ev",{"^->":"gedeonAppears.excccccellent1.0.c-0.$r2"},"/ev",{"temp=":"$r"},{"->":".^.^.4.s"},[{"#n":"$r2"}],"\n",{"->":".^.^.^.^.deidamiaAppears"},{"#f":5}]}],{"#f":1}],"youMussssst":[["^<em>\"You mussssst.\"</em>","\n",["ev",{"^->":"gedeonAppears.youMussssst.0.2.$r1"},{"temp=":"$r"},"str",{"->":".^.s"},[{"#n":"$r1"}],"/str","/ev",{"*":".^.^.c-0","flg":2},{"s":["^Next",{"->":"$r","var":true},null]}],{"c-0":["ev",{"^->":"gedeonAppears.youMussssst.0.c-0.$r2"},"/ev",{"temp=":"$r"},{"->":".^.^.2.s"},[{"#n":"$r2"}],"\n",{"->":".^.^.^.^.youHaveAlreadyPl"},{"#f":5}]}],{"#f":1}],"hmmmmm1":[["^<em>\"Hmmmmm\"</em>","\n",["ev",{"^->":"gedeonAppears.hmmmmm1.0.2.$r1"},{"temp=":"$r"},"str",{"->":".^.s"},[{"#n":"$r1"}],"/str","/ev",{"*":".^.^.c-0","flg":2},{"s":["^Next",{"->":"$r","var":true},null]}],{"c-0":["ev",{"^->":"gedeonAppears.hmmmmm1.0.c-0.$r2"},"/ev",{"temp=":"$r"},{"->":".^.^.2.s"},[{"#n":"$r2"}],"\n",{"->":".^.^.^.^.weFear"},{"#f":5}]}],{"#f":1}],"weDifferFarGreat":[["^<em>\"We differ far greater than I had anticccccipated.\"</em>","\n",["ev",{"^->":"gedeonAppears.weDifferFarGreat.0.2.$r1"},{"temp=":"$r"},"str",{"->":".^.s"},[{"#n":"$r1"}],"/str","/ev",{"*":".^.^.c-0","flg":2},{"s":["^Next",{"->":"$r","var":true},null]}],{"c-0":["ev",{"^->":"gedeonAppears.weDifferFarGreat.0.c-0.$r2"},"/ev",{"temp=":"$r"},{"->":".^.^.2.s"},[{"#n":"$r2"}],"\n",{"->":".^.^.^.^.iHowDisssssappoi"},{"#f":5}]}],{"#f":1}],"gedeonLooksAngry1":[["^Gedeon looks angry.","\n","^<i>\"You dare wassssste my time?\"</i>","\n",["ev",{"^->":"gedeonAppears.gedeonLooksAngry1.0.4.$r1"},{"temp=":"$r"},"str",{"->":".^.s"},[{"#n":"$r1"}],"/str","/ev",{"*":".^.^.c-0","flg":2},{"s":["^I just don't want to join",{"->":"$r","var":true},null]}],["ev",{"^->":"gedeonAppears.gedeonLooksAngry1.0.5.$r1"},{"temp=":"$r"},"str",{"->":".^.s"},[{"#n":"$r1"}],"/str","/ev",{"*":".^.^.c-1","flg":2},{"s":["^Yes",{"->":"$r","var":true},null]}],{"c-0":["ev",{"^->":"gedeonAppears.gedeonLooksAngry1.0.c-0.$r2"},"/ev",{"temp=":"$r"},{"->":".^.^.4.s"},[{"#n":"$r2"}],"\n",{"->":".^.^.^.^.punctuatedStitch2"},{"#f":5}],"c-1":["ev",{"^->":"gedeonAppears.gedeonLooksAngry1.0.c-1.$r2"},"/ev",{"temp=":"$r"},{"->":".^.^.5.s"},[{"#n":"$r2"}],"\n",{"->":".^.^.^.^.theRoomDarkens"},{"#f":5}]}],{"#f":1}],"youHaveAlreadyPl":[["^<em>\"You have already pledged.\"</em>","\n",["ev",{"^->":"gedeonAppears.youHaveAlreadyPl.0.2.$r1"},{"temp=":"$r"},"str",{"->":".^.s"},[{"#n":"$r1"}],"/str","/ev",{"*":".^.^.c-0","flg":2},{"s":["^Well, okay then",{"->":"$r","var":true},null]}],["ev",{"^->":"gedeonAppears.youHaveAlreadyPl.0.3.$r1"},{"temp=":"$r"},"str",{"->":".^.s"},[{"#n":"$r1"}],"/str","/ev",{"*":".^.^.c-1","flg":2},{"s":["^Well, I un-pledge",{"->":"$r","var":true},null]}],{"c-0":["ev",{"^->":"gedeonAppears.youHaveAlreadyPl.0.c-0.$r2"},"/ev",{"temp=":"$r"},{"->":".^.^.2.s"},[{"#n":"$r2"}],"\n",{"->":".^.^.^.^.youSsssseeReasss"},{"#f":5}],"c-1":["ev",{"^->":"gedeonAppears.youHaveAlreadyPl.0.c-1.$r2"},"/ev",{"temp=":"$r"},{"->":".^.^.3.s"},[{"#n":"$r2"}],"\n",{"->":".^.^.^.^.theOnlyWayOut"},{"#f":5}]}],{"#f":1}],"weFear":[["^<em>\"We fear...\"</em>","\n",["ev",{"^->":"gedeonAppears.weFear.0.2.$r1"},{"temp=":"$r"},"str",{"->":".^.s"},[{"#n":"$r1"}],"/str","/ev",{"*":".^.^.c-0","flg":2},{"s":["^Next",{"->":"$r","var":true},null]}],{"c-0":["ev",{"^->":"gedeonAppears.weFear.0.c-0.$r2"},"/ev",{"temp=":"$r"},{"->":".^.^.2.s"},[{"#n":"$r2"}],"\n",{"->":".^.^.^.^.weFindYourWork"},{"#f":5}]}],{"#f":1}],"deidamiaAppears":[["^Deidamia appears<em></em>","\n","^<em>\"....\"</em>","\n",["ev",{"^->":"gedeonAppears.deidamiaAppears.0.4.$r1"},{"temp=":"$r"},"str",{"->":".^.s"},[{"#n":"$r1"}],"/str","/ev",{"*":".^.^.c-0","flg":2},{"s":["^Next",{"->":"$r","var":true},null]}],{"c-0":["ev",{"^->":"gedeonAppears.deidamiaAppears.0.c-0.$r2"},"/ev",{"temp=":"$r"},{"->":".^.^.4.s"},[{"#n":"$r2"}],"\n",{"->":".^.^.^.^.heeell"},{"#f":5}]}],{"#f":1}],"punctuatedStitch2":[["^<em>\"....\"</em>","\n",["ev",{"^->":"gedeonAppears.punctuatedStitch2.0.2.$r1"},{"temp=":"$r"},"str",{"->":".^.s"},[{"#n":"$r1"}],"/str","/ev",{"*":".^.^.c-0","flg":2},{"s":["^Next",{"->":"$r","var":true},null]}],{"c-0":["ev",{"^->":"gedeonAppears.punctuatedStitch2.0.c-0.$r2"},"/ev",{"temp=":"$r"},{"->":".^.^.2.s"},[{"#n":"$r2"}],"\n",{"->":".^.^.^.^.thenIWillAllowYo"},{"#f":5}]}],{"#f":1}],"theRoomDarkens":["^The room darkens.","\n","^A random amount of time passes.","\n","^Gedeon's snake appears.","\n","^<strong>Abrupt Ending Unlocked: Maybe don't piss off the assassin? (Gedeon Edition)</strong>","\n","end",{"#f":1}],"youSsssseeReasss":[["^<em>\"You sssssee reassssson.\"</em>","\n",["ev",{"^->":"gedeonAppears.youSsssseeReasss.0.2.$r1"},{"temp=":"$r"},"str",{"->":".^.s"},[{"#n":"$r1"}],"/str","/ev",{"*":".^.^.c-0","flg":2},{"s":["^Next",{"->":"$r","var":true},null]}],{"c-0":["ev",{"^->":"gedeonAppears.youSsssseeReasss.0.c-0.$r2"},"/ev",{"temp=":"$r"},{"->":".^.^.2.s"},[{"#n":"$r2"}],"\n",{"->":".^.^.^.^.veryGood"},{"#f":5}]}],{"#f":1}],"weFindYourWork":[["^<em>\"We find your work...\"</em>","\n",["ev",{"^->":"gedeonAppears.weFindYourWork.0.2.$r1"},{"temp=":"$r"},"str",{"->":".^.s"},[{"#n":"$r1"}],"/str","/ev",{"*":".^.^.c-0","flg":2},{"s":["^Next",{"->":"$r","var":true},null]}],{"c-0":["ev",{"^->":"gedeonAppears.weFindYourWork.0.c-0.$r2"},"/ev",{"temp=":"$r"},{"->":".^.^.2.s"},[{"#n":"$r2"}],"\n",{"->":".^.^.^.^.sssssubssssstand"},{"#f":5}]}],{"#f":1}],"theOnlyWayOut":[["^<em>\"The only way out.\"</em>","\n",["ev",{"^->":"gedeonAppears.theOnlyWayOut.0.2.$r1"},{"temp=":"$r"},"str",{"->":".^.s"},[{"#n":"$r1"}],"/str","/ev",{"*":".^.^.c-0","flg":2},{"s":["^Next",{"->":"$r","var":true},null]}],{"c-0":["ev",{"^->":"gedeonAppears.theOnlyWayOut.0.c-0.$r2"},"/ev",{"temp=":"$r"},{"->":".^.^.2.s"},[{"#n":"$r2"}],"\n",{"->":".^.^.^.^.isssssThroughThe"},{"#f":5}]}],{"#f":1}],"thenIWillAllowYo":["^<em>\"Then I will allow you to live.\"</em>","\n","^Gedeon leaves.","\n","^<strong>Defaults to Normal Arc.</strong><em></em>","\n","end",{"#f":1}],"veryGood":[["^<em>\"Very good.\"</em>","\n",["ev",{"^->":"gedeonAppears.veryGood.0.2.$r1"},{"temp=":"$r"},"str",{"->":".^.s"},[{"#n":"$r1"}],"/str","/ev",{"*":".^.^.c-0","flg":2},{"s":["^Next",{"->":"$r","var":true},null]}],{"c-0":["ev",{"^->":"gedeonAppears.veryGood.0.c-0.$r2"},"/ev",{"temp=":"$r"},{"->":".^.^.2.s"},[{"#n":"$r2"}],"\n",{"->":".^.^.^.^.iNowi"},{"#f":5}]}],{"#f":1}],"sssssubssssstand":[["^<em>\"...sssssubssssstandard.\"</em>","\n",["ev",{"^->":"gedeonAppears.sssssubssssstand.0.2.$r1"},{"temp=":"$r"},"str",{"->":".^.s"},[{"#n":"$r1"}],"/str","/ev",{"*":".^.^.c-0","flg":2},{"s":["^Next",{"->":"$r","var":true},null]}],{"c-0":["ev",{"^->":"gedeonAppears.sssssubssssstand.0.c-0.$r2"},"/ev",{"temp=":"$r"},{"->":".^.^.2.s"},[{"#n":"$r2"}],"\n",{"->":".^.^.^.^.theGuildHasssssN"},{"#f":5}]}],{"#f":1}],"isssssThroughThe":[["^<em>\"Isssss through the passsssing of life.\"</em>","\n",["ev",{"^->":"gedeonAppears.isssssThroughThe.0.2.$r1"},{"temp=":"$r"},"str",{"->":".^.s"},[{"#n":"$r1"}],"/str","/ev",{"*":".^.^.c-0","flg":2},{"s":["^Well, where is it",{"->":"$r","var":true},null]}],["ev",{"^->":"gedeonAppears.isssssThroughThe.0.3.$r1"},{"temp=":"$r"},"str",{"->":".^.s"},[{"#n":"$r1"}],"/str","/ev",{"*":".^.^.c-1","flg":2},{"s":["^Okay",{"->":"$r","var":true},null]}],["ev",{"^->":"gedeonAppears.isssssThroughThe.0.4.$r1"},{"temp=":"$r"},"str",{"->":".^.s"},[{"#n":"$r1"}],"/str","/ev",{"*":".^.^.c-2","flg":2},{"s":["^So, what's this test?",{"->":"$r","var":true},null]}],{"c-0":["ev",{"^->":"gedeonAppears.isssssThroughThe.0.c-0.$r2"},"/ev",{"temp=":"$r"},{"->":".^.^.2.s"},[{"#n":"$r2"}],"\n",{"->":".^.^.^.^.punctuatedStitch3"},{"#f":5}],"c-1":["ev",{"^->":"gedeonAppears.isssssThroughThe.0.c-1.$r2"},"/ev",{"temp=":"$r"},{"->":".^.^.3.s"},[{"#n":"$r2"}],"\n",{"->":".^.^.^.^.thenAllowMe"},{"#f":5}],"c-2":["ev",{"^->":"gedeonAppears.isssssThroughThe.0.c-2.$r2"},"/ev",{"temp=":"$r"},{"->":".^.^.4.s"},[{"#n":"$r2"}],"\n",{"->":".^.^.^.^.weRequireYourSss"},{"#f":5}]}],{"#f":1}],"heeell":[["^<em>\"heeell....\"</em>","\n",["ev",{"^->":"gedeonAppears.heeell.0.2.$r1"},{"temp=":"$r"},"str",{"->":".^.s"},[{"#n":"$r1"}],"/str","/ev",{"*":".^.^.c-0","flg":2},{"s":["^Next",{"->":"$r","var":true},null]}],{"c-0":["ev",{"^->":"gedeonAppears.heeell.0.c-0.$r2"},"/ev",{"temp=":"$r"},{"->":".^.^.2.s"},[{"#n":"$r2"}],"\n",{"->":".^.^.^.^.ooo"},{"#f":5}]}],{"#f":1}],"iNowi":[["^<i>\"Now.\"</i>","\n",["ev",{"^->":"gedeonAppears.iNowi.0.2.$r1"},{"temp=":"$r"},"str",{"->":".^.s"},[{"#n":"$r1"}],"/str","/ev",{"*":".^.^.c-0","flg":2},{"s":["^Next",{"->":"$r","var":true},null]}],{"c-0":["ev",{"^->":"gedeonAppears.iNowi.0.c-0.$r2"},"/ev",{"temp=":"$r"},{"->":".^.^.2.s"},[{"#n":"$r2"}],"\n",{"->":".^.^.^.^.weRequireYourSss"},{"#f":5}]}],{"#f":1}],"theGuildHasssssN":[["^<em>\"The guild hasssss no ussssse for unssssskilled membersssss.\"</em>","\n",["ev",{"^->":"gedeonAppears.theGuildHasssssN.0.2.$r1"},{"temp=":"$r"},"str",{"->":".^.s"},[{"#n":"$r1"}],"/str","/ev",{"*":".^.^.c-0","flg":2},{"s":["^Next",{"->":"$r","var":true},null]}],{"c-0":["ev",{"^->":"gedeonAppears.theGuildHasssssN.0.c-0.$r2"},"/ev",{"temp=":"$r"},{"->":".^.^.2.s"},[{"#n":"$r2"}],"\n",{"->":".^.^.^.^.youAreHereby"},{"#f":5}]}],{"#f":1}],"punctuatedStitch3":[["^<em>\"....\"</em>","\n",["ev",{"^->":"gedeonAppears.punctuatedStitch3.0.2.$r1"},{"temp=":"$r"},"str",{"->":".^.s"},[{"#n":"$r1"}],"/str","/ev",{"*":".^.^.c-0","flg":2},{"s":["^Next",{"->":"$r","var":true},null]}],{"c-0":["ev",{"^->":"gedeonAppears.punctuatedStitch3.0.c-0.$r2"},"/ev",{"temp=":"$r"},{"->":".^.^.2.s"},[{"#n":"$r2"}],"\n",{"->":".^.^.^.^.perhapsssssIHave"},{"#f":5}]}],{"#f":1}],"thenAllowMe":[["^<em>\"Then allow me...\"</em>","\n",["ev",{"^->":"gedeonAppears.thenAllowMe.0.2.$r1"},{"temp=":"$r"},"str",{"->":".^.s"},[{"#n":"$r1"}],"/str","/ev",{"*":".^.^.c-0","flg":2},{"s":["^Next",{"->":"$r","var":true},null]}],{"c-0":["ev",{"^->":"gedeonAppears.thenAllowMe.0.c-0.$r2"},"/ev",{"temp=":"$r"},{"->":".^.^.2.s"},[{"#n":"$r2"}],"\n",{"->":".^.^.^.^.theRoomDarkens1"},{"#f":5}]}],{"#f":1}],"ooo":[["^<em>\"ooo...\"</em>","\n",["ev",{"^->":"gedeonAppears.ooo.0.2.$r1"},{"temp=":"$r"},"str",{"->":".^.s"},[{"#n":"$r1"}],"/str","/ev",{"*":".^.^.c-0","flg":2},{"s":["^Hey",{"->":"$r","var":true},null]}],{"c-0":["ev",{"^->":"gedeonAppears.ooo.0.c-0.$r2"},"/ev",{"temp=":"$r"},{"->":".^.^.2.s"},[{"#n":"$r2"}],"\n",{"->":".^.^.^.^.youuuHaaaveeePle"},{"#f":5}]}],{"#f":1}],"youAreHereby":[["^<em>\"You are hereby...\"</em>","\n",["ev",{"^->":"gedeonAppears.youAreHereby.0.2.$r1"},{"temp=":"$r"},"str",{"->":".^.s"},[{"#n":"$r1"}],"/str","/ev",{"*":".^.^.c-0","flg":2},{"s":["^....",{"->":"$r","var":true},null]}],["ev",{"^->":"gedeonAppears.youAreHereby.0.3.$r1"},{"temp=":"$r"},"str",{"->":".^.s"},[{"#n":"$r1"}],"/str","/ev",{"*":".^.^.c-1","flg":2},{"s":["^WAIT!",{"->":"$r","var":true},null]}],{"c-0":["ev",{"^->":"gedeonAppears.youAreHereby.0.c-0.$r2"},"/ev",{"temp=":"$r"},{"->":".^.^.2.s"},[{"#n":"$r2"}],"\n",{"->":".^.^.^.^.releasssssedOfYo"},{"#f":5}],"c-1":["ev",{"^->":"gedeonAppears.youAreHereby.0.c-1.$r2"},"/ev",{"temp=":"$r"},{"->":".^.^.3.s"},[{"#n":"$r2"}],"\n",{"->":".^.^.^.^.punctuatedStitch4"},{"#f":5}]}],{"#f":1}],"perhapsssssIHave":[["^<em>\"Perhapsssss I have confusssssed you.\"</em>","\n",["ev",{"^->":"gedeonAppears.perhapsssssIHave.0.2.$r1"},{"temp=":"$r"},"str",{"->":".^.s"},[{"#n":"$r1"}],"/str","/ev",{"*":".^.^.c-0","flg":2},{"s":["^Next",{"->":"$r","var":true},null]}],{"c-0":["ev",{"^->":"gedeonAppears.perhapsssssIHave.0.c-0.$r2"},"/ev",{"temp=":"$r"},{"->":".^.^.2.s"},[{"#n":"$r2"}],"\n",{"->":".^.^.^.^.insteadOfASssssl"},{"#f":5}]}],{"#f":1}],"theRoomDarkens1":["^The room darkens.","\n","^A random amount of time passes.","\n","^A snake appears.","\n","^<strong>Abrupt Ending Unlocked: Releassssed From Duty: Indefinitely</strong>","\n","end",{"#f":1}],"youuuHaaaveeePle":[["^<em>\"Youuu haaaveee pleeedgeeed.\"</em>","\n",["ev",{"^->":"gedeonAppears.youuuHaaaveeePle.0.2.$r1"},{"temp=":"$r"},"str",{"->":".^.s"},[{"#n":"$r1"}],"/str","/ev",{"*":".^.^.c-0","flg":2},{"s":["^Next",{"->":"$r","var":true},null]}],{"c-0":["ev",{"^->":"gedeonAppears.youuuHaaaveeePle.0.c-0.$r2"},"/ev",{"temp=":"$r"},{"->":".^.^.2.s"},[{"#n":"$r2"}],"\n",{"->":".^.^.^.^.aaandYouuurTeees"},{"#f":5}]}],{"#f":1}],"releasssssedOfYo":[["^<em>\"releasssssed of your resssssponsssssibilitiesssss...\"</em>","\n",["ev",{"^->":"gedeonAppears.releasssssedOfYo.0.2.$r1"},{"temp=":"$r"},"str",{"->":".^.s"},[{"#n":"$r1"}],"/str","/ev",{"*":".^.^.c-0","flg":2},{"s":["^Next",{"->":"$r","var":true},null]}],{"c-0":["ev",{"^->":"gedeonAppears.releasssssedOfYo.0.c-0.$r2"},"/ev",{"temp=":"$r"},{"->":".^.^.2.s"},[{"#n":"$r2"}],"\n",{"->":".^.^.^.^.theRoomDarkens1"},{"#f":5}]}],{"#f":1}],"insteadOfASssssl":[["^<em>\"Instead of a sssssly one, you appear to be a mere ignoramusssss.\"</em>","\n",["ev",{"^->":"gedeonAppears.insteadOfASssssl.0.2.$r1"},{"temp=":"$r"},"str",{"->":".^.s"},[{"#n":"$r1"}],"/str","/ev",{"*":".^.^.c-0","flg":2},{"s":["^Next",{"->":"$r","var":true},null]}],{"c-0":["ev",{"^->":"gedeonAppears.insteadOfASssssl.0.c-0.$r2"},"/ev",{"temp=":"$r"},{"->":".^.^.2.s"},[{"#n":"$r2"}],"\n",{"->":".^.^.^.^.whatIMeantYoungO"},{"#f":5}]}],{"#f":1}],"punctuatedStitch4":[["^<em>\"....\"</em>","\n",["ev",{"^->":"gedeonAppears.punctuatedStitch4.0.2.$r1"},{"temp=":"$r"},"str",{"->":".^.s"},[{"#n":"$r1"}],"/str","/ev",{"*":".^.^.c-0","flg":2},{"s":["^Next",{"->":"$r","var":true},null]}],{"c-0":["ev",{"^->":"gedeonAppears.punctuatedStitch4.0.c-0.$r2"},"/ev",{"temp=":"$r"},{"->":".^.^.2.s"},[{"#n":"$r2"}],"\n",{"->":".^.^.^.^.yesssss"},{"#f":5}]}],{"#f":1}],"aaandYouuurTeees":[["^<em>\"Aaand youuur teeessst.\"</em>","\n",["ev",{"^->":"gedeonAppears.aaandYouuurTeees.0.2.$r1"},{"temp=":"$r"},"str",{"->":".^.s"},[{"#n":"$r1"}],"/str","/ev",{"*":".^.^.c-0","flg":2},{"s":["^Next",{"->":"$r","var":true},null]}],{"c-0":["ev",{"^->":"gedeonAppears.aaandYouuurTeees.0.c-0.$r2"},"/ev",{"temp=":"$r"},{"->":".^.^.2.s"},[{"#n":"$r2"}],"\n",{"->":".^.^.^.^.waaasssDeeemeeed"},{"#f":5}]}],{"#f":1}],"whatIMeantYoungO":[["^<em>\"What I meant, young one.\"</em>","\n",["ev",{"^->":"gedeonAppears.whatIMeantYoungO.0.2.$r1"},{"temp=":"$r"},"str",{"->":".^.s"},[{"#n":"$r1"}],"/str","/ev",{"*":".^.^.c-0","flg":2},{"s":["^Next",{"->":"$r","var":true},null]}],{"c-0":["ev",{"^->":"gedeonAppears.whatIMeantYoungO.0.c-0.$r2"},"/ev",{"temp=":"$r"},{"->":".^.^.2.s"},[{"#n":"$r2"}],"\n",{"->":".^.^.^.^.isssssThatTheOnl"},{"#f":5}]}],{"#f":1}],"yesssss":[["^<em>\"Yesssss?\"</em>","\n",["ev",{"^->":"gedeonAppears.yesssss.0.2.$r1"},{"temp=":"$r"},"str",{"->":".^.s"},[{"#n":"$r1"}],"/str","/ev",{"*":".^.^.c-0","flg":2},{"s":["^Give me two days",{"->":"$r","var":true},null]}],{"c-0":["ev",{"^->":"gedeonAppears.yesssss.0.c-0.$r2"},"/ev",{"temp=":"$r"},{"->":".^.^.2.s"},[{"#n":"$r2"}],"\n",{"->":".^.^.^.^.punctuatedStitch5"},{"#f":5}]}],{"#f":1}],"waaasssDeeemeeed":[["^<em>\"Waaasss deeemeeed...\"</em>","\n",["ev",{"^->":"gedeonAppears.waaasssDeeemeeed.0.2.$r1"},{"temp=":"$r"},"str",{"->":".^.s"},[{"#n":"$r1"}],"/str","/ev",{"*":".^.^.c-0","flg":2},{"s":["^Next",{"->":"$r","var":true},null]}],{"c-0":["ev",{"^->":"gedeonAppears.waaasssDeeemeeed.0.c-0.$r2"},"/ev",{"temp=":"$r"},{"->":".^.^.2.s"},[{"#n":"$r2"}],"\n",{"->":".^.^.^.^.hmmm"},{"#f":5}]}],{"#f":1}],"isssssThatTheOnl":[["^<em>\"Isssss that the only way to leave the asssssasssssin's guild...\"</em>","\n",["ev",{"^->":"gedeonAppears.isssssThatTheOnl.0.2.$r1"},{"temp=":"$r"},"str",{"->":".^.s"},[{"#n":"$r1"}],"/str","/ev",{"*":".^.^.c-0","flg":2},{"s":["^Next",{"->":"$r","var":true},null]}],{"c-0":["ev",{"^->":"gedeonAppears.isssssThatTheOnl.0.c-0.$r2"},"/ev",{"temp=":"$r"},{"->":".^.^.2.s"},[{"#n":"$r2"}],"\n",{"->":".^.^.^.^.isssssDeath"},{"#f":5}]}],{"#f":1}],"punctuatedStitch5":[["^<em>\"....\"</em>","\n",["ev",{"^->":"gedeonAppears.punctuatedStitch5.0.2.$r1"},{"temp=":"$r"},"str",{"->":".^.s"},[{"#n":"$r1"}],"/str","/ev",{"*":".^.^.c-0","flg":2},{"s":["^Next",{"->":"$r","var":true},null]}],{"c-0":["ev",{"^->":"gedeonAppears.punctuatedStitch5.0.c-0.$r2"},"/ev",{"temp=":"$r"},{"->":".^.^.2.s"},[{"#n":"$r2"}],"\n",{"->":".^.^.^.^.youGetOne"},{"#f":5}]}],{"#f":1}],"hmmm":[["^<em>\"Hmmm...\"</em>","\n",["ev",{"^->":"gedeonAppears.hmmm.0.2.$r1"},{"temp=":"$r"},"str",{"->":".^.s"},[{"#n":"$r1"}],"/str","/ev",{"*":".^.^.c-0","flg":2},{"s":["^Next",{"->":"$r","var":true},null]}],{"c-0":["ev",{"^->":"gedeonAppears.hmmm.0.c-0.$r2"},"/ev",{"temp=":"$r"},{"->":".^.^.2.s"},[{"#n":"$r2"}],"\n",{"->":".^.^.^.^.tOleeerableee"},{"#f":5}]}],{"#f":1}],"isssssDeath":[["^<em>\"Isssss death.\"</em>","\n",["ev",{"^->":"gedeonAppears.isssssDeath.0.2.$r1"},{"temp=":"$r"},"str",{"->":".^.s"},[{"#n":"$r1"}],"/str","/ev",{"*":".^.^.c-0","flg":2},{"s":["^...oh",{"->":"$r","var":true},null]}],["ev",{"^->":"gedeonAppears.isssssDeath.0.3.$r1"},{"temp=":"$r"},"str",{"->":".^.s"},[{"#n":"$r1"}],"/str","/ev",{"*":".^.^.c-1","flg":2},{"s":["^I knew that",{"->":"$r","var":true},null]}],{"c-0":["ev",{"^->":"gedeonAppears.isssssDeath.0.c-0.$r2"},"/ev",{"temp=":"$r"},{"->":".^.^.2.s"},[{"#n":"$r2"}],"\n",{"->":".^.^.^.^.confirmed"},{"#f":5}],"c-1":["ev",{"^->":"gedeonAppears.isssssDeath.0.c-1.$r2"},"/ev",{"temp=":"$r"},{"->":".^.^.3.s"},[{"#n":"$r2"}],"\n",{"->":".^.^.^.^.ifYouInsssssisss"},{"#f":5}]}],{"#f":1}],"youGetOne":[["^<em>\"You get one.\"</em>","\n",["ev",{"^->":"gedeonAppears.youGetOne.0.2.$r1"},{"temp=":"$r"},"str",{"->":".^.s"},[{"#n":"$r1"}],"/str","/ev",{"*":".^.^.c-0","flg":2},{"s":["^Next",{"->":"$r","var":true},null]}],{"c-0":["ev",{"^->":"gedeonAppears.youGetOne.0.c-0.$r2"},"/ev",{"temp=":"$r"},{"->":".^.^.2.s"},[{"#n":"$r2"}],"\n",{"->":".^.^.^.^.doNotDisssssappo"},{"#f":5}]}],{"#f":1}],"tOleeerableee":[["^<em>\"tOleeerableee.\"</em>","\n",["ev",{"^->":"gedeonAppears.tOleeerableee.0.2.$r1"},{"temp=":"$r"},"str",{"->":".^.s"},[{"#n":"$r1"}],"/str","/ev",{"*":".^.^.c-0","flg":2},{"s":["^Next",{"->":"$r","var":true},null]}],{"c-0":["ev",{"^->":"gedeonAppears.tOleeerableee.0.c-0.$r2"},"/ev",{"temp=":"$r"},{"->":".^.^.2.s"},[{"#n":"$r2"}],"\n",{"->":".^.^.^.^.andSooo"},{"#f":5}]}],{"#f":1}],"doNotDisssssappo":[["^<em>\"Do not disssssappoint.\"</em>","\n","^Gedeon leaves.","\n",["ev",{"^->":"gedeonAppears.doNotDisssssappo.0.4.$r1"},{"temp=":"$r"},"str",{"->":".^.s"},[{"#n":"$r1"}],"/str","/ev",{"*":".^.^.c-0","flg":2},{"s":["^Next",{"->":"$r","var":true},null]}],{"c-0":["ev",{"^->":"gedeonAppears.doNotDisssssappo.0.c-0.$r2"},"/ev",{"temp=":"$r"},{"->":".^.^.4.s"},[{"#n":"$r2"}],"\n",{"->":".^.^.^.^.gedeonReturns"},{"#f":5}]}],{"#f":1}],"confirmed":[["^<em>\"Confirmed.\"</em>","\n",["ev",{"^->":"gedeonAppears.confirmed.0.2.$r1"},{"temp=":"$r"},"str",{"->":".^.s"},[{"#n":"$r1"}],"/str","/ev",{"*":".^.^.c-0","flg":2},{"s":["^Next",{"->":"$r","var":true},null]}],{"c-0":["ev",{"^->":"gedeonAppears.confirmed.0.c-0.$r2"},"/ev",{"temp=":"$r"},{"->":".^.^.2.s"},[{"#n":"$r2"}],"\n",{"->":".^.^.^.^.ignorumasssss"},{"#f":5}]}],{"#f":1}],"ifYouInsssssisss":[["^<em>\"If you insssssissssst.\"</em>","\n",["ev",{"^->":"gedeonAppears.ifYouInsssssisss.0.2.$r1"},{"temp=":"$r"},"str",{"->":".^.s"},[{"#n":"$r1"}],"/str","/ev",{"*":".^.^.c-0","flg":2},{"s":["^Next",{"->":"$r","var":true},null]}],{"c-0":["ev",{"^->":"gedeonAppears.ifYouInsssssisss.0.c-0.$r2"},"/ev",{"temp=":"$r"},{"->":".^.^.2.s"},[{"#n":"$r2"}],"\n",{"->":".^.^.^.^.iNowi"},{"#f":5}]}],{"#f":1}],"andSooo":[["^<em>\"And sooo...\"</em>","\n",["ev",{"^->":"gedeonAppears.andSooo.0.2.$r1"},{"temp=":"$r"},"str",{"->":".^.s"},[{"#n":"$r1"}],"/str","/ev",{"*":".^.^.c-0","flg":2},{"s":["^Next",{"->":"$r","var":true},null]}],{"c-0":["ev",{"^->":"gedeonAppears.andSooo.0.c-0.$r2"},"/ev",{"temp=":"$r"},{"->":".^.^.2.s"},[{"#n":"$r2"}],"\n",{"->":".^.^.^.^.iveComeToCaaallU"},{"#f":5}]}],{"#f":1}],"ignorumasssss":[["^<em>\"Ignorumasssss.\"</em>","\n",["ev",{"^->":"gedeonAppears.ignorumasssss.0.2.$r1"},{"temp=":"$r"},"str",{"->":".^.s"},[{"#n":"$r1"}],"/str","/ev",{"*":".^.^.c-0","flg":2},{"s":["^Next",{"->":"$r","var":true},null]}],{"c-0":["ev",{"^->":"gedeonAppears.ignorumasssss.0.c-0.$r2"},"/ev",{"temp=":"$r"},{"->":".^.^.2.s"},[{"#n":"$r2"}],"\n",{"->":".^.^.^.^.iNowi"},{"#f":5}]}],{"#f":1}],"iveComeToCaaallU":[["^<em>\"I've come to caaall upooon the pleeedgeee.\"</em>","\n",["ev",{"^->":"gedeonAppears.iveComeToCaaallU.0.2.$r1"},{"temp=":"$r"},"str",{"->":".^.s"},[{"#n":"$r1"}],"/str","/ev",{"*":".^.^.c-0","flg":2},{"s":["^Next",{"->":"$r","var":true},null]}],{"c-0":["ev",{"^->":"gedeonAppears.iveComeToCaaallU.0.c-0.$r2"},"/ev",{"temp=":"$r"},{"->":".^.^.2.s"},[{"#n":"$r2"}],"\n",{"->":".^.^.^.^.aDeathPotionAppe"},{"#f":5}]}],{"#f":1}],"gedeonReturns":[["^Gedeon returns.","\n","^<em>\"Greetingssss, little ignoramusssss.\" </em>","\n",["ev",{"^->":"gedeonAppears.gedeonReturns.0.4.$r1"},{"temp=":"$r"},"str",{"->":".^.s"},[{"#n":"$r1"}],"/str","/ev",{"*":".^.^.c-0","flg":2},{"s":["^Hello",{"->":"$r","var":true},null]}],["ev",{"^->":"gedeonAppears.gedeonReturns.0.5.$r1"},{"temp=":"$r"},"str",{"->":".^.s"},[{"#n":"$r1"}],"/str","/ev",{"*":".^.^.c-1","flg":2},{"s":["^Who are you again?",{"->":"$r","var":true},null]}],{"c-0":["ev",{"^->":"gedeonAppears.gedeonReturns.0.c-0.$r2"},"/ev",{"temp=":"$r"},{"->":".^.^.4.s"},[{"#n":"$r2"}],"\n",{"->":".^.^.^.^.iHopeForYourSsss"},{"#f":5}],"c-1":["ev",{"^->":"gedeonAppears.gedeonReturns.0.c-1.$r2"},"/ev",{"temp=":"$r"},{"->":".^.^.5.s"},[{"#n":"$r2"}],"\n",{"->":".^.^.^.^.youLiveUpToYourN"},{"#f":5}]}],{"#f":1}],"aDeathPotionAppe":[["^A death potion appears on the counter.","\n","^<em>\"Give that to the oneee naaameeeD.\"</em>","\n",["ev",{"^->":"gedeonAppears.aDeathPotionAppe.0.4.$r1"},{"temp=":"$r"},"str",{"->":".^.s"},[{"#n":"$r1"}],"/str","/ev",{"*":".^.^.c-0","flg":2},{"s":["^Next",{"->":"$r","var":true},null]}],{"c-0":["ev",{"^->":"gedeonAppears.aDeathPotionAppe.0.c-0.$r2"},"/ev",{"temp=":"$r"},{"->":".^.^.4.s"},[{"#n":"$r2"}],"\n",{"->":".^.^.^.^.punctuatedStitch6"},{"#f":5}]}],{"#f":1}],"iHopeForYourSsss":[["^<em>\"I hope, for your sssssake, that you have lived up to your purpossssse.\"</em>","\n",["ev",{"^->":"gedeonAppears.iHopeForYourSsss.0.2.$r1"},{"temp=":"$r"},"str",{"->":".^.s"},[{"#n":"$r1"}],"/str","/ev",{"*":".^.^.c-0","flg":2},{"s":["^Next",{"->":"$r","var":true},null]}],{"c-0":["ev",{"^->":"gedeonAppears.iHopeForYourSsss.0.c-0.$r2"},"/ev",{"temp=":"$r"},{"->":".^.^.2.s"},[{"#n":"$r2"}],"\n",{"->":".^.^.^.^.now"},{"#f":5}]}],{"#f":1}],"youLiveUpToYourN":[["^<em>\"You live up to your nickname.\"</em>","\n",["ev",{"^->":"gedeonAppears.youLiveUpToYourN.0.2.$r1"},{"temp=":"$r"},"str",{"->":".^.s"},[{"#n":"$r1"}],"/str","/ev",{"*":".^.^.c-0","flg":2},{"s":["^Next",{"->":"$r","var":true},null]}],{"c-0":["ev",{"^->":"gedeonAppears.youLiveUpToYourN.0.c-0.$r2"},"/ev",{"temp=":"$r"},{"->":".^.^.2.s"},[{"#n":"$r2"}],"\n",{"->":".^.^.^.^.nowEnoughPlaying"},{"#f":5}]}],{"#f":1}],"punctuatedStitch6":[["^<em>\"...\"</em>","\n",["ev",{"^->":"gedeonAppears.punctuatedStitch6.0.2.$r1"},{"temp=":"$r"},"str",{"->":".^.s"},[{"#n":"$r1"}],"/str","/ev",{"*":".^.^.c-0","flg":2},{"s":["^Next",{"->":"$r","var":true},null]}],{"c-0":["ev",{"^->":"gedeonAppears.punctuatedStitch6.0.c-0.$r2"},"/ev",{"temp=":"$r"},{"->":".^.^.2.s"},[{"#n":"$r2"}],"\n",{"->":".^.^.^.^.caaaiiin"},{"#f":5}]}],{"#f":1}],"now":[["^<em>\"Now.\"</em>","\n",["ev",{"^->":"gedeonAppears.now.0.2.$r1"},{"temp=":"$r"},"str",{"->":".^.s"},[{"#n":"$r1"}],"/str","/ev",{"*":".^.^.c-0","flg":2},{"s":["^Next",{"->":"$r","var":true},null]}],{"c-0":["ev",{"^->":"gedeonAppears.now.0.c-0.$r2"},"/ev",{"temp=":"$r"},{"->":".^.^.2.s"},[{"#n":"$r2"}],"\n",{"->":".^.^.^.^.whereIsssssIt"},{"#f":5}]}],{"#f":1}],"nowEnoughPlaying":[["^<em>\"Now, enough playing gamesssss.\"</em>","\n",["ev",{"^->":"gedeonAppears.nowEnoughPlaying.0.2.$r1"},{"temp=":"$r"},"str",{"->":".^.s"},[{"#n":"$r1"}],"/str","/ev",{"*":".^.^.c-0","flg":2},{"s":["^Next",{"->":"$r","var":true},null]}],{"c-0":["ev",{"^->":"gedeonAppears.nowEnoughPlaying.0.c-0.$r2"},"/ev",{"temp=":"$r"},{"->":".^.^.2.s"},[{"#n":"$r2"}],"\n",{"->":".^.^.^.^.whereIsssssIt"},{"#f":5}]}],{"#f":1}],"caaaiiin":[["^<em><strong>\"Caaaiiin\"</strong></em>","\n",["ev",{"^->":"gedeonAppears.caaaiiin.0.2.$r1"},{"temp=":"$r"},"str",{"->":".^.s"},[{"#n":"$r1"}],"/str","/ev",{"*":".^.^.c-0","flg":2},{"s":["^Next",{"->":"$r","var":true},null]}],{"c-0":["ev",{"^->":"gedeonAppears.caaaiiin.0.c-0.$r2"},"/ev",{"temp=":"$r"},{"->":".^.^.2.s"},[{"#n":"$r2"}],"\n",{"->":".^.^.^.^.heWearsssThisssH"},{"#f":5}]}],{"#f":1}],"whereIsssssIt":[["^<em>\"Where isssss it.\"</em>","\n",["ev",{"^->":"gedeonAppears.whereIsssssIt.0.2.$r1"},{"temp=":"$r"},"str",{"->":".^.s"},[{"#n":"$r1"}],"/str","/ev",{"*":".^.^.c-0","flg":2},{"s":["^Death Potion",{"->":"$r","var":true},null]}],["ev",{"^->":"gedeonAppears.whereIsssssIt.0.3.$r1"},{"temp=":"$r"},"str",{"->":".^.s"},[{"#n":"$r1"}],"/str","/ev",{"*":".^.^.c-1","flg":2},{"s":["^Other Potion",{"->":"$r","var":true},null]}],{"c-0":["ev",{"^->":"gedeonAppears.whereIsssssIt.0.c-0.$r2"},"/ev",{"temp=":"$r"},{"->":".^.^.2.s"},[{"#n":"$r2"}],"\n",{"->":".^.^.^.^.punctuatedStitch7"},{"#f":5}],"c-1":["ev",{"^->":"gedeonAppears.whereIsssssIt.0.c-1.$r2"},"/ev",{"temp=":"$r"},{"->":".^.^.3.s"},[{"#n":"$r2"}],"\n",{"->":".^.^.^.^.punctuatedStitch8"},{"#f":5}]}],{"#f":1}],"heWearsssThisssH":[["^<em>\"He wearsss thisss <strong>hideousss </strong>bolerooo haaat aaand...\"</em>","\n",["ev",{"^->":"gedeonAppears.heWearsssThisssH.0.2.$r1"},{"temp=":"$r"},"str",{"->":".^.s"},[{"#n":"$r1"}],"/str","/ev",{"*":".^.^.c-0","flg":2},{"s":["^Next",{"->":"$r","var":true},null]}],{"c-0":["ev",{"^->":"gedeonAppears.heWearsssThisssH.0.c-0.$r2"},"/ev",{"temp=":"$r"},{"->":".^.^.2.s"},[{"#n":"$r2"}],"\n",{"->":".^.^.^.^.ressspiratooor"},{"#f":5}]}],{"#f":1}],"punctuatedStitch7":[["^<em>“….”</em>","\n",["ev",{"^->":"gedeonAppears.punctuatedStitch7.0.2.$r1"},{"temp=":"$r"},"str",{"->":".^.s"},[{"#n":"$r1"}],"/str","/ev",{"*":".^.^.c-0","flg":2},{"s":["^Next",{"->":"$r","var":true},null]}],{"c-0":["ev",{"^->":"gedeonAppears.punctuatedStitch7.0.c-0.$r2"},"/ev",{"temp=":"$r"},{"->":".^.^.2.s"},[{"#n":"$r2"}],"\n",{"->":".^.^.^.^.good1"},{"#f":5}]}],{"#f":1}],"punctuatedStitch8":[["^\"....\"","\n",["ev",{"^->":"gedeonAppears.punctuatedStitch8.0.2.$r1"},{"temp=":"$r"},"str",{"->":".^.s"},[{"#n":"$r1"}],"/str","/ev",{"*":".^.^.c-0","flg":2},{"s":["^Next",{"->":"$r","var":true},null]}],{"c-0":["ev",{"^->":"gedeonAppears.punctuatedStitch8.0.c-0.$r2"},"/ev",{"temp=":"$r"},{"->":".^.^.2.s"},[{"#n":"$r2"}],"\n",{"->":".^.^.^.^.youHaveDaredToWa"},{"#f":5}]}],{"#f":1}],"ressspiratooor":[["^<em>\"Ressspiratooor.\"</em>","\n",["ev",{"^->":"gedeonAppears.ressspiratooor.0.2.$r1"},{"temp=":"$r"},"str",{"->":".^.s"},[{"#n":"$r1"}],"/str","/ev",{"*":".^.^.c-0","flg":2},{"s":["^Next",{"->":"$r","var":true},null]}],{"c-0":["ev",{"^->":"gedeonAppears.ressspiratooor.0.c-0.$r2"},"/ev",{"temp=":"$r"},{"->":".^.^.2.s"},[{"#n":"$r2"}],"\n",{"->":".^.^.^.^.heeeavensss"},{"#f":5}]}],{"#f":1}],"good1":[["^<em>“Good”</em>","\n","^Gedeon leaves.","\n",["ev",{"^->":"gedeonAppears.good1.0.4.$r1"},{"temp=":"$r"},"str",{"->":".^.s"},[{"#n":"$r1"}],"/str","/ev",{"*":".^.^.c-0","flg":2},{"s":["^Next",{"->":"$r","var":true},null]}],{"c-0":["ev",{"^->":"gedeonAppears.good1.0.c-0.$r2"},"/ev",{"temp=":"$r"},{"->":".^.^.4.s"},[{"#n":"$r2"}],"\n",{"->":".^.^.^.^.deidamiaAppears"},{"#f":5}]}],{"#f":1}],"youHaveDaredToWa":[["^<em>\"You have dared to wassssste my time.\"</em>","\n",["ev",{"^->":"gedeonAppears.youHaveDaredToWa.0.2.$r1"},{"temp=":"$r"},"str",{"->":".^.s"},[{"#n":"$r1"}],"/str","/ev",{"*":".^.^.c-0","flg":2},{"s":["^Next",{"->":"$r","var":true},null]}],{"c-0":["ev",{"^->":"gedeonAppears.youHaveDaredToWa.0.c-0.$r2"},"/ev",{"temp=":"$r"},{"->":".^.^.2.s"},[{"#n":"$r2"}],"\n",{"->":".^.^.^.^.perhapsssssYouWi"},{"#f":5}]}],{"#f":1}],"heeeavensss":[["^<em>\"Heeeavensss\"</em>","\n",["ev",{"^->":"gedeonAppears.heeeavensss.0.2.$r1"},{"temp=":"$r"},"str",{"->":".^.s"},[{"#n":"$r1"}],"/str","/ev",{"*":".^.^.c-0","flg":2},{"s":["^Next",{"->":"$r","var":true},null]}],{"c-0":["ev",{"^->":"gedeonAppears.heeeavensss.0.c-0.$r2"},"/ev",{"temp=":"$r"},{"->":".^.^.2.s"},[{"#n":"$r2"}],"\n",{"->":".^.^.^.^.iHaaateThatMaaan"},{"#f":5}]}],{"#f":1}],"perhapsssssYouWi":[["^<em>\"Perhapsssss you will wisssssen up in your next life.\"</em>","\n",["ev",{"^->":"gedeonAppears.perhapsssssYouWi.0.2.$r1"},{"temp=":"$r"},"str",{"->":".^.s"},[{"#n":"$r1"}],"/str","/ev",{"*":".^.^.c-0","flg":2},{"s":["^Next",{"->":"$r","var":true},null]}],{"c-0":["ev",{"^->":"gedeonAppears.perhapsssssYouWi.0.c-0.$r2"},"/ev",{"temp=":"$r"},{"->":".^.^.2.s"},[{"#n":"$r2"}],"\n",{"->":".^.^.^.^.theRoomDarkens"},{"#f":5}]}],{"#f":1}],"iHaaateThatMaaan":[["^<em>\"I haaate that maaan.\"</em>","\n",["ev",{"^->":"gedeonAppears.iHaaateThatMaaan.0.2.$r1"},{"temp=":"$r"},"str",{"->":".^.s"},[{"#n":"$r1"}],"/str","/ev",{"*":".^.^.c-0","flg":2},{"s":["^Next",{"->":"$r","var":true},null]}],{"c-0":["ev",{"^->":"gedeonAppears.iHaaateThatMaaan.0.c-0.$r2"},"/ev",{"temp=":"$r"},{"->":".^.^.2.s"},[{"#n":"$r2"}],"\n",{"->":".^.^.^.^.killlHimmm"},{"#f":5}]}],{"#f":1}],"killlHimmm":[["^<em>\"Killl himmm.\"</em>","\n",["ev",{"^->":"gedeonAppears.killlHimmm.0.2.$r1"},{"temp=":"$r"},"str",{"->":".^.s"},[{"#n":"$r1"}],"/str","/ev",{"*":".^.^.c-0","flg":2},{"s":["^Next",{"->":"$r","var":true},null]}],{"c-0":["ev",{"^->":"gedeonAppears.killlHimmm.0.c-0.$r2"},"/ev",{"temp=":"$r"},{"->":".^.^.2.s"},[{"#n":"$r2"}],"\n",{"->":".^.^.^.^.befoooreHeee"},{"#f":5}]}],{"#f":1}],"befoooreHeee":[["^<em>\"Befooore heee...\"</em>","\n",["ev",{"^->":"gedeonAppears.befoooreHeee.0.2.$r1"},{"temp=":"$r"},"str",{"->":".^.s"},[{"#n":"$r1"}],"/str","/ev",{"*":".^.^.c-0","flg":2},{"s":["^Next",{"->":"$r","var":true},null]}],{"c-0":["ev",{"^->":"gedeonAppears.befoooreHeee.0.c-0.$r2"},"/ev",{"temp=":"$r"},{"->":".^.^.2.s"},[{"#n":"$r2"}],"\n",{"->":".^.^.^.^.killsssAlllOfUss"},{"#f":5}]}],{"#f":1}],"killsssAlllOfUss":[["^<em>\"Killsss alll of usss.\"</em>","\n",["ev",{"^->":"gedeonAppears.killsssAlllOfUss.0.2.$r1"},{"temp=":"$r"},"str",{"->":".^.s"},[{"#n":"$r1"}],"/str","/ev",{"*":".^.^.c-0","flg":2},{"s":["^Next",{"->":"$r","var":true},null]}],{"c-0":["ev",{"^->":"gedeonAppears.killsssAlllOfUss.0.c-0.$r2"},"/ev",{"temp=":"$r"},{"->":".^.^.2.s"},[{"#n":"$r2"}],"\n",{"->":".^.^.^.^.yeaaa"},{"#f":5}]}],{"#f":1}],"yeaaa":[["^<em>\"Yeaaa?\"</em>","\n",["ev",{"^->":"gedeonAppears.yeaaa.0.2.$r1"},{"temp=":"$r"},"str",{"->":".^.s"},[{"#n":"$r1"}],"/str","/ev",{"*":".^.^.c-0","flg":2},{"s":["^...",{"->":"$r","var":true},null]}],["ev",{"^->":"gedeonAppears.yeaaa.0.3.$r1"},{"temp=":"$r"},"str",{"->":".^.s"},[{"#n":"$r1"}],"/str","/ev",{"*":".^.^.c-1","flg":2},{"s":["^Got it",{"->":"$r","var":true},null]}],["ev",{"^->":"gedeonAppears.yeaaa.0.4.$r1"},{"temp=":"$r"},"str",{"->":".^.s"},[{"#n":"$r1"}],"/str","/ev",{"*":".^.^.c-2","flg":2},{"s":["^No",{"->":"$r","var":true},null]}],{"c-0":["ev",{"^->":"gedeonAppears.yeaaa.0.c-0.$r2"},"/ev",{"temp=":"$r"},{"->":".^.^.2.s"},[{"#n":"$r2"}],"\n",{"->":".^.^.^.^.heeell1"},{"#f":5}],"c-1":["ev",{"^->":"gedeonAppears.yeaaa.0.c-1.$r2"},"/ev",{"temp=":"$r"},{"->":".^.^.3.s"},[{"#n":"$r2"}],"\n",{"->":".^.^.^.^.goood"},{"#f":5}],"c-2":["ev",{"^->":"gedeonAppears.yeaaa.0.c-2.$r2"},"/ev",{"temp=":"$r"},{"->":".^.^.4.s"},[{"#n":"$r2"}],"\n",{"->":".^.^.^.^.punctuatedStitch9"},{"#f":5}]}],{"#f":1}],"heeell1":[["^<em>\"Heeell...\"</em>","\n",["ev",{"^->":"gedeonAppears.heeell1.0.2.$r1"},{"temp=":"$r"},"str",{"->":".^.s"},[{"#n":"$r1"}],"/str","/ev",{"*":".^.^.c-0","flg":2},{"s":["^Next",{"->":"$r","var":true},null]}],{"c-0":["ev",{"^->":"gedeonAppears.heeell1.0.c-0.$r2"},"/ev",{"temp=":"$r"},{"->":".^.^.2.s"},[{"#n":"$r2"}],"\n",{"->":".^.^.^.^.oooo"},{"#f":5}]}],{"#f":1}],"goood":[["^<em>\"Goood.\"</em>","\n","^Deidamia leaves.<em></em>","\n",["ev",{"^->":"gedeonAppears.goood.0.4.$r1"},{"temp=":"$r"},"str",{"->":".^.s"},[{"#n":"$r1"}],"/str","/ev",{"*":".^.^.c-0","flg":2},{"s":["^Next",{"->":"$r","var":true},null]}],{"c-0":["ev",{"^->":"gedeonAppears.goood.0.c-0.$r2"},"/ev",{"temp=":"$r"},{"->":".^.^.4.s"},[{"#n":"$r2"}],"\n",{"->":".^.^.^.^.cainAppears"},{"#f":5}]}],{"#f":1}],"punctuatedStitch9":[["^<em>\"....\"</em>","\n",["ev",{"^->":"gedeonAppears.punctuatedStitch9.0.2.$r1"},{"temp=":"$r"},"str",{"->":".^.s"},[{"#n":"$r1"}],"/str","/ev",{"*":".^.^.c-0","flg":2},{"s":["^Next",{"->":"$r","var":true},null]}],{"c-0":["ev",{"^->":"gedeonAppears.punctuatedStitch9.0.c-0.$r2"},"/ev",{"temp=":"$r"},{"->":".^.^.2.s"},[{"#n":"$r2"}],"\n",{"->":".^.^.^.^.teeellMeee"},{"#f":5}]}],{"#f":1}],"oooo":[["^<em>\"oooo...\"</em>","\n",["ev",{"^->":"gedeonAppears.oooo.0.2.$r1"},{"temp=":"$r"},"str",{"->":".^.s"},[{"#n":"$r1"}],"/str","/ev",{"*":".^.^.c-0","flg":2},{"s":["^Next",{"->":"$r","var":true},null]}],{"c-0":["ev",{"^->":"gedeonAppears.oooo.0.c-0.$r2"},"/ev",{"temp=":"$r"},{"->":".^.^.2.s"},[{"#n":"$r2"}],"\n",{"->":".^.^.^.^.wakeUuup"},{"#f":5}]}],{"#f":1}],"teeellMeee":[["^<em>\"Teeell meee...\"</em>","\n",["ev",{"^->":"gedeonAppears.teeellMeee.0.2.$r1"},{"temp=":"$r"},"str",{"->":".^.s"},[{"#n":"$r1"}],"/str","/ev",{"*":".^.^.c-0","flg":2},{"s":["^Next",{"->":"$r","var":true},null]}],{"c-0":["ev",{"^->":"gedeonAppears.teeellMeee.0.c-0.$r2"},"/ev",{"temp=":"$r"},{"->":".^.^.2.s"},[{"#n":"$r2"}],"\n",{"->":".^.^.^.^.doooYouuuWishhhT"},{"#f":5}]}],{"#f":1}],"wakeUuup":[["^<em>\"Wake uuup.\"</em>","\n",["ev",{"^->":"gedeonAppears.wakeUuup.0.2.$r1"},{"temp=":"$r"},"str",{"->":".^.s"},[{"#n":"$r1"}],"/str","/ev",{"*":".^.^.c-0","flg":2},{"s":["^Next",{"->":"$r","var":true},null]}],{"c-0":["ev",{"^->":"gedeonAppears.wakeUuup.0.c-0.$r2"},"/ev",{"temp=":"$r"},{"->":".^.^.2.s"},[{"#n":"$r2"}],"\n",{"->":".^.^.^.^.werrreSsspeaking"},{"#f":5}]}],{"#f":1}],"doooYouuuWishhhT":[["^<em>\"Dooo youuu wishhh to diiie?\"</em>","\n",["ev",{"^->":"gedeonAppears.doooYouuuWishhhT.0.2.$r1"},{"temp=":"$r"},"str",{"->":".^.s"},[{"#n":"$r1"}],"/str","/ev",{"*":".^.^.c-0","flg":2},{"s":["^....",{"->":"$r","var":true},null]}],["ev",{"^->":"gedeonAppears.doooYouuuWishhhT.0.3.$r1"},{"temp=":"$r"},"str",{"->":".^.s"},[{"#n":"$r1"}],"/str","/ev",{"*":".^.^.c-1","flg":2},{"s":["^Yes",{"->":"$r","var":true},null]}],["ev",{"^->":"gedeonAppears.doooYouuuWishhhT.0.4.$r1"},{"temp=":"$r"},"str",{"->":".^.s"},[{"#n":"$r1"}],"/str","/ev",{"*":".^.^.c-2","flg":2},{"s":["^No",{"->":"$r","var":true},null]}],{"c-0":["ev",{"^->":"gedeonAppears.doooYouuuWishhhT.0.c-0.$r2"},"/ev",{"temp=":"$r"},{"->":".^.^.2.s"},[{"#n":"$r2"}],"\n",{"->":".^.^.^.^.yesssOrNooo"},{"#f":5}],"c-1":["ev",{"^->":"gedeonAppears.doooYouuuWishhhT.0.c-1.$r2"},"/ev",{"temp=":"$r"},{"->":".^.^.3.s"},[{"#n":"$r2"}],"\n",{"->":".^.^.^.^.punctuatedStitch10"},{"#f":5}],"c-2":["ev",{"^->":"gedeonAppears.doooYouuuWishhhT.0.c-2.$r2"},"/ev",{"temp=":"$r"},{"->":".^.^.4.s"},[{"#n":"$r2"}],"\n",{"->":".^.^.^.^.theeennnDoooAsss"},{"#f":5}]}],{"#f":1}],"cainAppears":[["^Cain appears.","\n","^\"Greetings partner, K-k-kshhhhh\"","\n",["ev",{"^->":"gedeonAppears.cainAppears.0.4.$r1"},{"temp=":"$r"},"str",{"->":".^.s"},[{"#n":"$r1"}],"/str","/ev",{"*":".^.^.c-0","flg":2},{"s":["^Next",{"->":"$r","var":true},null]}],{"c-0":["ev",{"^->":"gedeonAppears.cainAppears.0.c-0.$r2"},"/ev",{"temp=":"$r"},{"->":".^.^.4.s"},[{"#n":"$r2"}],"\n",{"->":".^.^.^.^.fearIGotNickedGa"},{"#f":5}]}],{"#f":1}],"werrreSsspeaking":[["^<em>\"We'rrre ssspeakinggg heeerrre\"</em>","\n",["ev",{"^->":"gedeonAppears.werrreSsspeaking.0.2.$r1"},{"temp=":"$r"},"str",{"->":".^.s"},[{"#n":"$r1"}],"/str","/ev",{"*":".^.^.c-0","flg":2},{"s":["^Oops",{"->":"$r","var":true},null]}],["ev",{"^->":"gedeonAppears.werrreSsspeaking.0.3.$r1"},{"temp=":"$r"},"str",{"->":".^.s"},[{"#n":"$r1"}],"/str","/ev",{"*":".^.^.c-1","flg":2},{"s":["^Right, got it",{"->":"$r","var":true},null]}],{"c-0":["ev",{"^->":"gedeonAppears.werrreSsspeaking.0.c-0.$r2"},"/ev",{"temp=":"$r"},{"->":".^.^.2.s"},[{"#n":"$r2"}],"\n",{"->":".^.^.^.^.deidamiaLooksAng"},{"#f":5}],"c-1":["ev",{"^->":"gedeonAppears.werrreSsspeaking.0.c-1.$r2"},"/ev",{"temp=":"$r"},{"->":".^.^.3.s"},[{"#n":"$r2"}],"\n",{"->":".^.^.^.^.goood"},{"#f":5}]}],{"#f":1}],"yesssOrNooo":[["^<em>\"Yesss or Nooo?\"</em>","\n",["ev",{"^->":"gedeonAppears.yesssOrNooo.0.2.$r1"},{"temp=":"$r"},"str",{"->":".^.s"},[{"#n":"$r1"}],"/str","/ev",{"*":".^.^.c-0","flg":2},{"s":["^Yes",{"->":"$r","var":true},null]}],["ev",{"^->":"gedeonAppears.yesssOrNooo.0.3.$r1"},{"temp=":"$r"},"str",{"->":".^.s"},[{"#n":"$r1"}],"/str","/ev",{"*":".^.^.c-1","flg":2},{"s":["^No",{"->":"$r","var":true},null]}],{"c-0":["ev",{"^->":"gedeonAppears.yesssOrNooo.0.c-0.$r2"},"/ev",{"temp=":"$r"},{"->":".^.^.2.s"},[{"#n":"$r2"}],"\n",{"->":".^.^.^.^.punctuatedStitch10"},{"#f":5}],"c-1":["ev",{"^->":"gedeonAppears.yesssOrNooo.0.c-1.$r2"},"/ev",{"temp=":"$r"},{"->":".^.^.3.s"},[{"#n":"$r2"}],"\n",{"->":".^.^.^.^.theeennnDoooAsss"},{"#f":5}]}],{"#f":1}],"punctuatedStitch10":[["^<em>\"....\"</em>","\n",["ev",{"^->":"gedeonAppears.punctuatedStitch10.0.2.$r1"},{"temp=":"$r"},"str",{"->":".^.s"},[{"#n":"$r1"}],"/str","/ev",{"*":".^.^.c-0","flg":2},{"s":["^Next",{"->":"$r","var":true},null]}],{"c-0":["ev",{"^->":"gedeonAppears.punctuatedStitch10.0.c-0.$r2"},"/ev",{"temp=":"$r"},{"->":".^.^.2.s"},[{"#n":"$r2"}],"\n",{"->":".^.^.^.^.welll"},{"#f":5}]}],{"#f":1}],"theeennnDoooAsss":[["^<em>\"Theeennn dooo asss you'rrre tooold.\"</em>","\n","^Deidamia leaves.<em></em>","\n",["ev",{"^->":"gedeonAppears.theeennnDoooAsss.0.4.$r1"},{"temp=":"$r"},"str",{"->":".^.s"},[{"#n":"$r1"}],"/str","/ev",{"*":".^.^.c-0","flg":2},{"s":["^Next",{"->":"$r","var":true},null]}],{"c-0":["ev",{"^->":"gedeonAppears.theeennnDoooAsss.0.c-0.$r2"},"/ev",{"temp=":"$r"},{"->":".^.^.4.s"},[{"#n":"$r2"}],"\n",{"->":".^.^.^.^.cainAppears"},{"#f":5}]}],{"#f":1}],"deidamiaLooksAng":[["^Deidamia looks angry.<em></em>","\n","^<i>\"...\"</i>","\n",["ev",{"^->":"gedeonAppears.deidamiaLooksAng.0.4.$r1"},{"temp=":"$r"},"str",{"->":".^.s"},[{"#n":"$r1"}],"/str","/ev",{"*":".^.^.c-0","flg":2},{"s":["^Next",{"->":"$r","var":true},null]}],{"c-0":["ev",{"^->":"gedeonAppears.deidamiaLooksAng.0.c-0.$r2"},"/ev",{"temp=":"$r"},{"->":".^.^.4.s"},[{"#n":"$r2"}],"\n",{"->":".^.^.^.^.ooopsss"},{"#f":5}]}],{"#f":1}],"welll":[["^<em>\"Welll....\"</em>","\n",["ev",{"^->":"gedeonAppears.welll.0.2.$r1"},{"temp=":"$r"},"str",{"->":".^.s"},[{"#n":"$r1"}],"/str","/ev",{"*":".^.^.c-0","flg":2},{"s":["^Next",{"->":"$r","var":true},null]}],{"c-0":["ev",{"^->":"gedeonAppears.welll.0.c-0.$r2"},"/ev",{"temp=":"$r"},{"->":".^.^.2.s"},[{"#n":"$r2"}],"\n",{"->":".^.^.^.^.ifYouInsssissst"},{"#f":5}]}],{"#f":1}],"fearIGotNickedGa":[["^\"Fear I got nicked 'gain.\"","\n",["ev",{"^->":"gedeonAppears.fearIGotNickedGa.0.2.$r1"},{"temp=":"$r"},"str",{"->":".^.s"},[{"#n":"$r1"}],"/str","/ev",{"*":".^.^.c-0","flg":2},{"s":["^Next",{"->":"$r","var":true},null]}],{"c-0":["ev",{"^->":"gedeonAppears.fearIGotNickedGa.0.c-0.$r2"},"/ev",{"temp=":"$r"},{"->":".^.^.2.s"},[{"#n":"$r2"}],"\n",{"->":".^.^.^.^.butImAboveSnakes"},{"#f":5}]}],{"#f":1}],"ifYouInsssissst":[["^<em>\"If you insssissst.\"</em>","\n",["ev",{"^->":"gedeonAppears.ifYouInsssissst.0.2.$r1"},{"temp=":"$r"},"str",{"->":".^.s"},[{"#n":"$r1"}],"/str","/ev",{"*":".^.^.c-0","flg":2},{"s":["^Next",{"->":"$r","var":true},null]}],{"c-0":["ev",{"^->":"gedeonAppears.ifYouInsssissst.0.c-0.$r2"},"/ev",{"temp=":"$r"},{"->":".^.^.2.s"},[{"#n":"$r2"}],"\n",{"->":".^.^.^.^.theRoomDarkens1"},{"#f":5}]}],{"#f":1}],"butImAboveSnakes":[["^\"But I'm above snakes yet 'gain K-kshhh\"","\n",["ev",{"^->":"gedeonAppears.butImAboveSnakes.0.2.$r1"},{"temp=":"$r"},"str",{"->":".^.s"},[{"#n":"$r1"}],"/str","/ev",{"*":".^.^.c-0","flg":2},{"s":["^Next",{"->":"$r","var":true},null]}],{"c-0":["ev",{"^->":"gedeonAppears.butImAboveSnakes.0.c-0.$r2"},"/ev",{"temp=":"$r"},{"->":".^.^.2.s"},[{"#n":"$r2"}],"\n",{"->":".^.^.^.^.iHearYaGotTheBes"},{"#f":5}]}],{"#f":1}],"ooopsss":[["^<em>\"Ooopsss?!\"</em>","\n",["ev",{"^->":"gedeonAppears.ooopsss.0.2.$r1"},{"temp=":"$r"},"str",{"->":".^.s"},[{"#n":"$r1"}],"/str","/ev",{"*":".^.^.c-0","flg":2},{"s":["^Next",{"->":"$r","var":true},null]}],{"c-0":["ev",{"^->":"gedeonAppears.ooopsss.0.c-0.$r2"},"/ev",{"temp=":"$r"},{"->":".^.^.2.s"},[{"#n":"$r2"}],"\n",{"->":".^.^.^.^.whaaatDoooYouuuM"},{"#f":5}]}],{"#f":1}],"iHearYaGotTheBes":[["^\"I hear ya got the best antidotes money can buy 'round these parts.\"","\n",["ev",{"^->":"gedeonAppears.iHearYaGotTheBes.0.2.$r1"},{"temp=":"$r"},"str",{"->":".^.s"},[{"#n":"$r1"}],"/str","/ev",{"*":".^.^.c-0","flg":2},{"s":["^Next",{"->":"$r","var":true},null]}],{"c-0":["ev",{"^->":"gedeonAppears.iHearYaGotTheBes.0.c-0.$r2"},"/ev",{"temp=":"$r"},{"->":".^.^.2.s"},[{"#n":"$r2"}],"\n",{"->":".^.^.^.^.justWonderingIfT"},{"#f":5}]}],{"#f":1}],"whaaatDoooYouuuM":[["^<em>\"Whaaat dooo youuu meeeannn....\"</em>","\n",["ev",{"^->":"gedeonAppears.whaaatDoooYouuuM.0.2.$r1"},{"temp=":"$r"},"str",{"->":".^.s"},[{"#n":"$r1"}],"/str","/ev",{"*":".^.^.c-0","flg":2},{"s":["^Next",{"->":"$r","var":true},null]}],{"c-0":["ev",{"^->":"gedeonAppears.whaaatDoooYouuuM.0.c-0.$r2"},"/ev",{"temp=":"$r"},{"->":".^.^.2.s"},[{"#n":"$r2"}],"\n",{"->":".^.^.^.^.oooopssss"},{"#f":5}]}],{"#f":1}],"justWonderingIfT":[["^\"Just wondering if that were true? K-kshhh\"","\n",["ev",{"^->":"gedeonAppears.justWonderingIfT.0.2.$r1"},{"temp=":"$r"},"str",{"->":".^.s"},[{"#n":"$r1"}],"/str","/ev",{"*":".^.^.c-0","flg":2},{"s":["^Yes",{"->":"$r","var":true},null]}],["ev",{"^->":"gedeonAppears.justWonderingIfT.0.3.$r1"},{"temp=":"$r"},"str",{"->":".^.s"},[{"#n":"$r1"}],"/str","/ev",{"*":".^.^.c-1","flg":2},{"s":["^No",{"->":"$r","var":true},null]}],{"c-0":["ev",{"^->":"gedeonAppears.justWonderingIfT.0.c-0.$r2"},"/ev",{"temp=":"$r"},{"->":".^.^.2.s"},[{"#n":"$r2"}],"\n",{"->":".^.^.^.^.thatRight"},{"#f":5}],"c-1":["ev",{"^->":"gedeonAppears.justWonderingIfT.0.c-1.$r2"},"/ev",{"temp=":"$r"},{"->":".^.^.3.s"},[{"#n":"$r2"}],"\n",{"->":".^.^.^.^.mightyShame"},{"#f":5}]}],{"#f":1}],"oooopssss":[["^<em><strong>\"Oooopssss?!!\"</strong></em>","\n",["ev",{"^->":"gedeonAppears.oooopssss.0.2.$r1"},{"temp=":"$r"},"str",{"->":".^.s"},[{"#n":"$r1"}],"/str","/ev",{"*":".^.^.c-0","flg":2},{"s":["^I'm kidding!",{"->":"$r","var":true},null]}],["ev",{"^->":"gedeonAppears.oooopssss.0.3.$r1"},{"temp=":"$r"},"str",{"->":".^.s"},[{"#n":"$r1"}],"/str","/ev",{"*":".^.^.c-1","flg":2},{"s":["^I was ignoring you",{"->":"$r","var":true},null]}],{"c-0":["ev",{"^->":"gedeonAppears.oooopssss.0.c-0.$r2"},"/ev",{"temp=":"$r"},{"->":".^.^.2.s"},[{"#n":"$r2"}],"\n",{"->":".^.^.^.^.youuuBessstBeee"},{"#f":5}],"c-1":["ev",{"^->":"gedeonAppears.oooopssss.0.c-1.$r2"},"/ev",{"temp=":"$r"},{"->":".^.^.3.s"},[{"#n":"$r2"}],"\n",{"->":".^.^.^.^.deidamiaLooksPis"},{"#f":5}]}],{"#f":1}],"thatRight":[["^\"That right?\"","\n",["ev",{"^->":"gedeonAppears.thatRight.0.2.$r1"},{"temp=":"$r"},"str",{"->":".^.s"},[{"#n":"$r1"}],"/str","/ev",{"*":".^.^.c-0","flg":2},{"s":["^Next",{"->":"$r","var":true},null]}],{"c-0":["ev",{"^->":"gedeonAppears.thatRight.0.c-0.$r2"},"/ev",{"temp=":"$r"},{"->":".^.^.2.s"},[{"#n":"$r2"}],"\n",{"->":".^.^.^.^.wellInThatCaseKk"},{"#f":5}]}],{"#f":1}],"mightyShame":[["^\"Mighty shame.\"","\n",["ev",{"^->":"gedeonAppears.mightyShame.0.2.$r1"},{"temp=":"$r"},"str",{"->":".^.s"},[{"#n":"$r1"}],"/str","/ev",{"*":".^.^.c-0","flg":2},{"s":["^....",{"->":"$r","var":true},null]}],["ev",{"^->":"gedeonAppears.mightyShame.0.3.$r1"},{"temp=":"$r"},"str",{"->":".^.s"},[{"#n":"$r1"}],"/str","/ev",{"*":".^.^.c-1","flg":2},{"s":["^I've got something better",{"->":"$r","var":true},null]}],{"c-0":["ev",{"^->":"gedeonAppears.mightyShame.0.c-0.$r2"},"/ev",{"temp=":"$r"},{"->":".^.^.2.s"},[{"#n":"$r2"}],"\n",{"->":".^.^.^.^.butISupposeNotAl"},{"#f":5}],"c-1":["ev",{"^->":"gedeonAppears.mightyShame.0.c-1.$r2"},"/ev",{"temp=":"$r"},{"->":".^.^.3.s"},[{"#n":"$r2"}],"\n",{"->":".^.^.^.^.imListeningKkshh"},{"#f":5}]}],{"#f":1}],"youuuBessstBeee":[["^<em>\"Youuu bessst beee.\"</em>","\n",["ev",{"^->":"gedeonAppears.youuuBessstBeee.0.2.$r1"},{"temp=":"$r"},"str",{"->":".^.s"},[{"#n":"$r1"}],"/str","/ev",{"*":".^.^.c-0","flg":2},{"s":["^Next",{"->":"$r","var":true},null]}],{"c-0":["ev",{"^->":"gedeonAppears.youuuBessstBeee.0.c-0.$r2"},"/ev",{"temp=":"$r"},{"->":".^.^.2.s"},[{"#n":"$r2"}],"\n",{"->":".^.^.^.^.ifYouuuVaaaluuue"},{"#f":5}]}],{"#f":1}],"deidamiaLooksPis":[["^Deidamia looks pissed.","\n","^<em>\"Are you atteeempting to enraaage usss!!\"</em>","\n",["ev",{"^->":"gedeonAppears.deidamiaLooksPis.0.4.$r1"},{"temp=":"$r"},"str",{"->":".^.s"},[{"#n":"$r1"}],"/str","/ev",{"*":".^.^.c-0","flg":2},{"s":["^Next",{"->":"$r","var":true},null]}],{"c-0":["ev",{"^->":"gedeonAppears.deidamiaLooksPis.0.c-0.$r2"},"/ev",{"temp=":"$r"},{"->":".^.^.4.s"},[{"#n":"$r2"}],"\n",{"->":".^.^.^.^.punctuatedStitch11"},{"#f":5}]}],{"#f":1}],"wellInThatCaseKk":[["^\"Well, in that case...K-k-kshhhhh\"","\n",["ev",{"^->":"gedeonAppears.wellInThatCaseKk.0.2.$r1"},{"temp=":"$r"},"str",{"->":".^.s"},[{"#n":"$r1"}],"/str","/ev",{"*":".^.^.c-0","flg":2},{"s":["^Next",{"->":"$r","var":true},null]}],{"c-0":["ev",{"^->":"gedeonAppears.wellInThatCaseKk.0.c-0.$r2"},"/ev",{"temp=":"$r"},{"->":".^.^.2.s"},[{"#n":"$r2"}],"\n",{"->":".^.^.^.^.mindHelpingABrot"},{"#f":5}]}],{"#f":1}],"butISupposeNotAl":[["^\"But I 'suppose not all rumors can be true K-k-kshhhh\"","\n",["ev",{"^->":"gedeonAppears.butISupposeNotAl.0.2.$r1"},{"temp=":"$r"},"str",{"->":".^.s"},[{"#n":"$r1"}],"/str","/ev",{"*":".^.^.c-0","flg":2},{"s":["^Next",{"->":"$r","var":true},null]}],{"c-0":["ev",{"^->":"gedeonAppears.butISupposeNotAl.0.c-0.$r2"},"/ev",{"temp=":"$r"},{"->":".^.^.2.s"},[{"#n":"$r2"}],"\n",{"->":".^.^.^.^.bestOfLuckToYa"},{"#f":5}]}],{"#f":1}],"imListeningKkshh":[["^\"I'm listening k-kshhh\"","\n",["ev",{"^->":"gedeonAppears.imListeningKkshh.0.2.$r1"},{"temp=":"$r"},"str",{"->":".^.s"},[{"#n":"$r1"}],"/str","/ev",{"*":".^.^.c-0","flg":2},{"s":["^6th Sense",{"->":"$r","var":true},null]}],["ev",{"^->":"gedeonAppears.imListeningKkshh.0.3.$r1"},{"temp=":"$r"},"str",{"->":".^.s"},[{"#n":"$r1"}],"/str","/ev",{"*":".^.^.c-1","flg":2},{"s":["^Other Potion",{"->":"$r","var":true},null]}],{"c-0":["ev",{"^->":"gedeonAppears.imListeningKkshh.0.c-0.$r2"},"/ev",{"temp=":"$r"},{"->":".^.^.2.s"},[{"#n":"$r2"}],"\n",{"->":".^.^.^.^.wellIllBe"},{"#f":5}],"c-1":["ev",{"^->":"gedeonAppears.imListeningKkshh.0.c-1.$r2"},"/ev",{"temp=":"$r"},{"->":".^.^.3.s"},[{"#n":"$r2"}],"\n",{"->":".^.^.^.^.punctuatedStitch14"},{"#f":5}]}],{"#f":1}],"ifYouuuVaaaluuue":[["^<em>\"If youuu vaaaluuue your liiife.\"</em>","\n",["ev",{"^->":"gedeonAppears.ifYouuuVaaaluuue.0.2.$r1"},{"temp=":"$r"},"str",{"->":".^.s"},[{"#n":"$r1"}],"/str","/ev",{"*":".^.^.c-0","flg":2},{"s":["^Next",{"->":"$r","var":true},null]}],{"c-0":["ev",{"^->":"gedeonAppears.ifYouuuVaaaluuue.0.c-0.$r2"},"/ev",{"temp=":"$r"},{"->":".^.^.2.s"},[{"#n":"$r2"}],"\n",{"->":".^.^.^.^.iRecommmennnD"},{"#f":5}]}],{"#f":1}],"mindHelpingABrot":[["^\"Mind helping a brother out?\"","\n",["ev",{"^->":"gedeonAppears.mindHelpingABrot.0.2.$r1"},{"temp=":"$r"},"str",{"->":".^.s"},[{"#n":"$r1"}],"/str","/ev",{"*":".^.^.c-0","flg":2},{"s":["^Deidamia's Poison",{"->":"$r","var":true},null]}],["ev",{"^->":"gedeonAppears.mindHelpingABrot.0.3.$r1"},{"temp=":"$r"},"str",{"->":".^.s"},[{"#n":"$r1"}],"/str","/ev",{"*":".^.^.c-1","flg":2},{"s":["^Antidote",{"->":"$r","var":true},null]}],{"c-0":["ev",{"^->":"gedeonAppears.mindHelpingABrot.0.c-0.$r2"},"/ev",{"temp=":"$r"},{"->":".^.^.2.s"},[{"#n":"$r2"}],"\n",{"->":".^.^.^.^.muchObligedKkshh"},{"#f":5}],"c-1":["ev",{"^->":"gedeonAppears.mindHelpingABrot.0.c-1.$r2"},"/ev",{"temp=":"$r"},{"->":".^.^.3.s"},[{"#n":"$r2"}],"\n",{"->":".^.^.^.^.mightyKindOfYaKk"},{"#f":5}]}],{"#f":1}],"bestOfLuckToYa":[["^\"Best of luck to ya.\"","\n","^Cain leaves.","\n",["ev",{"^->":"gedeonAppears.bestOfLuckToYa.0.4.$r1"},{"temp=":"$r"},"str",{"->":".^.s"},[{"#n":"$r1"}],"/str","/ev",{"*":".^.^.c-0","flg":2},{"s":["^Next",{"->":"$r","var":true},null]}],{"c-0":["ev",{"^->":"gedeonAppears.bestOfLuckToYa.0.c-0.$r2"},"/ev",{"temp=":"$r"},{"->":".^.^.4.s"},[{"#n":"$r2"}],"\n",{"->":".^.^.^.^.gedeonAppearsLoo"},{"#f":5}]}],{"#f":1}],"wellIllBe":[["^\"Well, I'll be...\"","\n","ev",true,"/ev",{"VAR=":"6th_sense","re":true},"ev",true,"/ev",{"VAR=":"helpedcain","re":true},["ev",{"^->":"gedeonAppears.wellIllBe.0.10.$r1"},{"temp=":"$r"},"str",{"->":".^.s"},[{"#n":"$r1"}],"/str","/ev",{"*":".^.^.c-0","flg":2},{"s":["^Next",{"->":"$r","var":true},null]}],{"c-0":["ev",{"^->":"gedeonAppears.wellIllBe.0.c-0.$r2"},"/ev",{"temp=":"$r"},{"->":".^.^.10.s"},[{"#n":"$r2"}],"\n",{"->":".^.^.^.^.ifThisWorksAsInt"},{"#f":5}]}],{"#f":1}],"punctuatedStitch14":[["^\"....\"","\n",["ev",{"^->":"gedeonAppears.punctuatedStitch14.0.2.$r1"},{"temp=":"$r"},"str",{"->":".^.s"},[{"#n":"$r1"}],"/str","/ev",{"*":".^.^.c-0","flg":2},{"s":["^Next",{"->":"$r","var":true},null]}],{"c-0":["ev",{"^->":"gedeonAppears.punctuatedStitch14.0.c-0.$r2"},"/ev",{"temp=":"$r"},{"->":".^.^.2.s"},[{"#n":"$r2"}],"\n",{"->":".^.^.^.^.kkkshhhhh"},{"#f":5}]}],{"#f":1}],"punctuatedStitch11":[["^\"...\"","\n",["ev",{"^->":"gedeonAppears.punctuatedStitch11.0.2.$r1"},{"temp=":"$r"},"str",{"->":".^.s"},[{"#n":"$r1"}],"/str","/ev",{"*":".^.^.c-0","flg":2},{"s":["^Next",{"->":"$r","var":true},null]}],{"c-0":["ev",{"^->":"gedeonAppears.punctuatedStitch11.0.c-0.$r2"},"/ev",{"temp=":"$r"},{"->":".^.^.2.s"},[{"#n":"$r2"}],"\n",{"->":".^.^.^.^.deidamiaReturnsT"},{"#f":5}]}],{"#f":1}],"iRecommmennnD":[["^<em>\"I recommmennnD...\"</em>","\n",["ev",{"^->":"gedeonAppears.iRecommmennnD.0.2.$r1"},{"temp=":"$r"},"str",{"->":".^.s"},[{"#n":"$r1"}],"/str","/ev",{"*":".^.^.c-0","flg":2},{"s":["^Next",{"->":"$r","var":true},null]}],{"c-0":["ev",{"^->":"gedeonAppears.iRecommmennnD.0.c-0.$r2"},"/ev",{"temp=":"$r"},{"->":".^.^.2.s"},[{"#n":"$r2"}],"\n",{"->":".^.^.^.^.noooTTeeesssting"},{"#f":5}]}],{"#f":1}],"muchObligedKkshh":[["^\"Much obliged K-kshhh\"","\n","^Cain leaves.","\n",["ev",{"^->":"gedeonAppears.muchObligedKkshh.0.4.$r1"},{"temp=":"$r"},"str",{"->":".^.s"},[{"#n":"$r1"}],"/str","/ev",{"*":".^.^.c-0","flg":2},{"s":["^Next",{"->":"$r","var":true},null]}],{"c-0":["ev",{"^->":"gedeonAppears.muchObligedKkshh.0.c-0.$r2"},"/ev",{"temp=":"$r"},{"->":".^.^.4.s"},[{"#n":"$r2"}],"\n",{"->":".^.^.^.^.deidamiaReturns"},{"#f":5}]}],{"#f":1}],"mightyKindOfYaKk":[["^\"Mighty kind of ya K-kshhh\"","\n","ev",true,"/ev",{"VAR=":"antidote","re":true},"ev",true,"/ev",{"VAR=":"helpedcain","re":true},["ev",{"^->":"gedeonAppears.mightyKindOfYaKk.0.10.$r1"},{"temp=":"$r"},"str",{"->":".^.s"},[{"#n":"$r1"}],"/str","/ev",{"*":".^.^.c-0","flg":2},{"s":["^Next",{"->":"$r","var":true},null]}],{"c-0":["ev",{"^->":"gedeonAppears.mightyKindOfYaKk.0.c-0.$r2"},"/ev",{"temp=":"$r"},{"->":".^.^.10.s"},[{"#n":"$r2"}],"\n",{"->":".^.^.^.^.illBeSeeingYaRou"},{"#f":5}]}],{"#f":1}],"ifThisWorksAsInt":[["^\"If this works as intended? K-k-kshhhhh\"","\n",["ev",{"^->":"gedeonAppears.ifThisWorksAsInt.0.2.$r1"},{"temp=":"$r"},"str",{"->":".^.s"},[{"#n":"$r1"}],"/str","/ev",{"*":".^.^.c-0","flg":2},{"s":["^Next",{"->":"$r","var":true},null]}],{"c-0":["ev",{"^->":"gedeonAppears.ifThisWorksAsInt.0.c-0.$r2"},"/ev",{"temp=":"$r"},{"->":".^.^.2.s"},[{"#n":"$r2"}],"\n",{"->":".^.^.^.^.wellIReckonYoull"},{"#f":5}]}],{"#f":1}],"kkkshhhhh":[["^\"K-k-kshhhhh\"","\n",["ev",{"^->":"gedeonAppears.kkkshhhhh.0.2.$r1"},{"temp=":"$r"},"str",{"->":".^.s"},[{"#n":"$r1"}],"/str","/ev",{"*":".^.^.c-0","flg":2},{"s":["^Next",{"->":"$r","var":true},null]}],{"c-0":["ev",{"^->":"gedeonAppears.kkkshhhhh.0.c-0.$r2"},"/ev",{"temp=":"$r"},{"->":".^.^.2.s"},[{"#n":"$r2"}],"\n",{"->":".^.^.^.^.wellThereAintNoN"},{"#f":5}]}],{"#f":1}],"deidamiaReturnsT":[["^Deidamia returns to looking angry.","\n","^<em>\"Becaussse it'sss nooot going to wooork.\"</em>","\n",["ev",{"^->":"gedeonAppears.deidamiaReturnsT.0.4.$r1"},{"temp=":"$r"},"str",{"->":".^.s"},[{"#n":"$r1"}],"/str","/ev",{"*":".^.^.c-0","flg":2},{"s":["^Just calm down, sweety",{"->":"$r","var":true},null]}],["ev",{"^->":"gedeonAppears.deidamiaReturnsT.0.5.$r1"},{"temp=":"$r"},"str",{"->":".^.s"},[{"#n":"$r1"}],"/str","/ev",{"*":".^.^.c-1","flg":2},{"s":["^....",{"->":"$r","var":true},null]}],{"c-0":["ev",{"^->":"gedeonAppears.deidamiaReturnsT.0.c-0.$r2"},"/ev",{"temp=":"$r"},{"->":".^.^.4.s"},[{"#n":"$r2"}],"\n",{"->":".^.^.^.^.theRoomDarkens2"},{"#f":5}],"c-1":["ev",{"^->":"gedeonAppears.deidamiaReturnsT.0.c-1.$r2"},"/ev",{"temp=":"$r"},{"->":".^.^.5.s"},[{"#n":"$r2"}],"\n",{"->":".^.^.^.^.ifYouuuVaaaluuue"},{"#f":5}]}],{"#f":1}],"noooTTeeesssting":[["^<em>\"noooT teeesssting usss.\"</em>","\n",["ev",{"^->":"gedeonAppears.noooTTeeesssting.0.2.$r1"},{"temp=":"$r"},"str",{"->":".^.s"},[{"#n":"$r1"}],"/str","/ev",{"*":".^.^.c-0","flg":2},{"s":["^Not even a little?",{"->":"$r","var":true},null]}],["ev",{"^->":"gedeonAppears.noooTTeeesssting.0.3.$r1"},{"temp=":"$r"},"str",{"->":".^.s"},[{"#n":"$r1"}],"/str","/ev",{"*":".^.^.c-1","flg":2},{"s":["^I understand",{"->":"$r","var":true},null]}],{"c-0":["ev",{"^->":"gedeonAppears.noooTTeeesssting.0.c-0.$r2"},"/ev",{"temp=":"$r"},{"->":".^.^.2.s"},[{"#n":"$r2"}],"\n",{"->":".^.^.^.^.theRoomDarkens3"},{"#f":5}],"c-1":["ev",{"^->":"gedeonAppears.noooTTeeesssting.0.c-1.$r2"},"/ev",{"temp=":"$r"},{"->":".^.^.3.s"},[{"#n":"$r2"}],"\n",{"->":".^.^.^.^.goood"},{"#f":5}]}],{"#f":1}],"gedeonAppearsLoo":[["^Gedeon appears looking angry.","\n","^<em>\"It has come to my attention that you have failed at your asssssignment.\"</em>","\n",["ev",{"^->":"gedeonAppears.gedeonAppearsLoo.0.4.$r1"},{"temp=":"$r"},"str",{"->":".^.s"},[{"#n":"$r1"}],"/str","/ev",{"*":".^.^.c-0","flg":2},{"s":["^Next",{"->":"$r","var":true},null]}],{"c-0":["ev",{"^->":"gedeonAppears.gedeonAppearsLoo.0.c-0.$r2"},"/ev",{"temp=":"$r"},{"->":".^.^.4.s"},[{"#n":"$r2"}],"\n",{"->":".^.^.^.^.failureIsNotAccc"},{"#f":5}]}],{"#f":1}],"illBeSeeingYaRou":[["^\"I'll be seeing ya 'round.\"","\n","^Cain leaves.","\n",["ev",{"^->":"gedeonAppears.illBeSeeingYaRou.0.4.$r1"},{"temp=":"$r"},"str",{"->":".^.s"},[{"#n":"$r1"}],"/str","/ev",{"*":".^.^.c-0","flg":2},{"s":["^Next",{"->":"$r","var":true},null]}],{"c-0":["ev",{"^->":"gedeonAppears.illBeSeeingYaRou.0.c-0.$r2"},"/ev",{"temp=":"$r"},{"->":".^.^.4.s"},[{"#n":"$r2"}],"\n",{"->":".^.^.^.^.theRoomDarkens4"},{"#f":5}]}],{"#f":1}],"wellIReckonYoull":[["^\"Well, I reckon you'll have yourself a loyal customer.\"","\n",["ev",{"^->":"gedeonAppears.wellIReckonYoull.0.2.$r1"},{"temp=":"$r"},"str",{"->":".^.s"},[{"#n":"$r1"}],"/str","/ev",{"*":".^.^.c-0","flg":2},{"s":["^Next",{"->":"$r","var":true},null]}],{"c-0":["ev",{"^->":"gedeonAppears.wellIReckonYoull.0.c-0.$r2"},"/ev",{"temp=":"$r"},{"->":".^.^.2.s"},[{"#n":"$r2"}],"\n",{"->":".^.^.^.^.muchObligedKkshh1"},{"#f":5}]}],{"#f":1}],"wellThereAintNoN":[["^\"Well, there ain't no need to lie to me, partner.\"","\n",["ev",{"^->":"gedeonAppears.wellThereAintNoN.0.2.$r1"},{"temp=":"$r"},"str",{"->":".^.s"},[{"#n":"$r1"}],"/str","/ev",{"*":".^.^.c-0","flg":2},{"s":["^Next",{"->":"$r","var":true},null]}],{"c-0":["ev",{"^->":"gedeonAppears.wellThereAintNoN.0.c-0.$r2"},"/ev",{"temp=":"$r"},{"->":".^.^.2.s"},[{"#n":"$r2"}],"\n",{"->":".^.^.^.^.iBestBeOffNowKks"},{"#f":5}]}],{"#f":1}],"theRoomDarkens3":[["^The room darkens.","\n","^\"....\"","\n",["ev",{"^->":"gedeonAppears.theRoomDarkens3.0.4.$r1"},{"temp=":"$r"},"str",{"->":".^.s"},[{"#n":"$r1"}],"/str","/ev",{"*":".^.^.c-0","flg":2},{"s":["^....",{"->":"$r","var":true},null]}],["ev",{"^->":"gedeonAppears.theRoomDarkens3.0.5.$r1"},{"temp=":"$r"},"str",{"->":".^.s"},[{"#n":"$r1"}],"/str","/ev",{"*":".^.^.c-1","flg":2},{"s":["^I'll take that as a no",{"->":"$r","var":true},null]}],{"c-0":["ev",{"^->":"gedeonAppears.theRoomDarkens3.0.c-0.$r2"},"/ev",{"temp=":"$r"},{"->":".^.^.4.s"},[{"#n":"$r2"}],"\n",{"->":".^.^.^.^.theRoomDarkensEv"},{"#f":5}],"c-1":["ev",{"^->":"gedeonAppears.theRoomDarkens3.0.c-1.$r2"},"/ev",{"temp=":"$r"},{"->":".^.^.5.s"},[{"#n":"$r2"}],"\n",{"->":".^.^.^.^.goood"},{"#f":5}]}],{"#f":1}],"deidamiaReturns":[["^Deidamia returns.","\n","^<em> \"I aaam pleeeasssed.\"</em>","\n",["ev",{"^->":"gedeonAppears.deidamiaReturns.0.4.$r1"},{"temp=":"$r"},"str",{"->":".^.s"},[{"#n":"$r1"}],"/str","/ev",{"*":".^.^.c-0","flg":2},{"s":["^Next",{"->":"$r","var":true},null]}],{"c-0":["ev",{"^->":"gedeonAppears.deidamiaReturns.0.c-0.$r2"},"/ev",{"temp=":"$r"},{"->":".^.^.4.s"},[{"#n":"$r2"}],"\n",{"->":".^.^.^.^.youuHaaveDooonnn"},{"#f":5}]}],{"#f":1}],"muchObligedKkshh1":[["^\"Much obliged K-kshhh'\"","\n","^Cain leaves","\n",["ev",{"^->":"gedeonAppears.muchObligedKkshh1.0.4.$r1"},{"temp=":"$r"},"str",{"->":".^.s"},[{"#n":"$r1"}],"/str","/ev",{"*":".^.^.c-0","flg":2},{"s":["^Next",{"->":"$r","var":true},null]}],{"c-0":["ev",{"^->":"gedeonAppears.muchObligedKkshh1.0.c-0.$r2"},"/ev",{"temp=":"$r"},{"->":".^.^.4.s"},[{"#n":"$r2"}],"\n",{"->":".^.^.^.^.gedeonAppearsLoo"},{"#f":5}]}],{"#f":1}],"iBestBeOffNowKks":[["^\"I best be off now k-kshhh\"","\n","^Cain leaves.","\n",["ev",{"^->":"gedeonAppears.iBestBeOffNowKks.0.4.$r1"},{"temp=":"$r"},"str",{"->":".^.s"},[{"#n":"$r1"}],"/str","/ev",{"*":".^.^.c-0","flg":2},{"s":["^Next",{"->":"$r","var":true},null]}],{"c-0":["ev",{"^->":"gedeonAppears.iBestBeOffNowKks.0.c-0.$r2"},"/ev",{"temp=":"$r"},{"->":".^.^.4.s"},[{"#n":"$r2"}],"\n",{"->":".^.^.^.^.gedeonAppearsLoo"},{"#f":5}]}],{"#f":1}],"theRoomDarkens2":[["^The room darkens.","\n","^Deidamia looks pissed.","\n","^\"..........\"","\n",["ev",{"^->":"gedeonAppears.theRoomDarkens2.0.6.$r1"},{"temp=":"$r"},"str",{"->":".^.s"},[{"#n":"$r1"}],"/str","/ev",{"*":".^.^.c-0","flg":2},{"s":["^Next",{"->":"$r","var":true},null]}],{"c-0":["ev",{"^->":"gedeonAppears.theRoomDarkens2.0.c-0.$r2"},"/ev",{"temp=":"$r"},{"->":".^.^.6.s"},[{"#n":"$r2"}],"\n",{"->":".^.^.^.^.foool"},{"#f":5}]}],{"#f":1}],"theRoomDarkens4":["^The room darkens.","\n",{"->":".^.^.gedeonAppearsLoo"},{"#f":1}],"failureIsNotAccc":[["^<em>\"Failure is <strong>not </strong>accccceptable.\"</em>","\n",["ev",{"^->":"gedeonAppears.failureIsNotAccc.0.2.$r1"},{"temp=":"$r"},"str",{"->":".^.s"},[{"#n":"$r1"}],"/str","/ev",{"*":".^.^.c-0","flg":2},{"s":["^Next",{"->":"$r","var":true},null]}],{"c-0":["ev",{"^->":"gedeonAppears.failureIsNotAccc.0.c-0.$r2"},"/ev",{"temp=":"$r"},{"->":".^.^.2.s"},[{"#n":"$r2"}],"\n",{"->":".^.^.^.^.theRoomDarkensEv1"},{"#f":5}]}],{"#f":1}],"theRoomDarkensEv":["^The room darkens even more.","\n","^Random amount of time passes.","\n","^Diedamia's Snake appears.","\n","^<em><strong>\"DIIIE!!\"</strong></em>","\n","^<strong>Abrupt Ending Unlocked: Maybe don't piss off the assassin? (Deidamia Edition)</strong>","\n","end",{"#f":1}],"youuHaaveDooonnn":[["^<em>\"Youu haave dooonnne <strong>veeerrry </strong>weeelll.\"</em><em></em>","\n",["ev",{"^->":"gedeonAppears.youuHaaveDooonnn.0.2.$r1"},{"temp=":"$r"},"str",{"->":".^.s"},[{"#n":"$r1"}],"/str","/ev",{"*":".^.^.c-0","flg":2},{"s":["^Next",{"->":"$r","var":true},null]}],{"c-0":["ev",{"^->":"gedeonAppears.youuHaaveDooonnn.0.c-0.$r2"},"/ev",{"temp=":"$r"},{"->":".^.^.2.s"},[{"#n":"$r2"}],"\n",{"->":".^.^.^.^.aCoinBagAppearsO"},{"#f":5}]}],{"#f":1}],"theRoomDarkensEv1":[["^The room darkens even more.","\n","^<em>\"Now, you mussssst die!\"</em>","\n",["ev",{"^->":"gedeonAppears.theRoomDarkensEv1.0.4.$r1"},{"temp=":"$r"},"str",{"->":".^.s"},[{"#n":"$r1"}],"/str",{"VAR?":"helpedcain"},"/ev",{"*":".^.^.c-0","flg":3},{"s":["^Next",{"->":"$r","var":true},null]}],["ev",{"^->":"gedeonAppears.theRoomDarkensEv1.0.5.$r1"},{"temp=":"$r"},"str",{"->":".^.s"},[{"#n":"$r1"}],"/str",{"VAR?":"helpedcain"},"!","/ev",{"*":".^.^.c-1","flg":3},{"s":["^Next",{"->":"$r","var":true},null]}],{"c-0":["ev",{"^->":"gedeonAppears.theRoomDarkensEv1.0.c-0.$r2"},"/ev",{"temp=":"$r"},{"->":".^.^.4.s"},[{"#n":"$r2"}],"\n",{"->":".^.^.^.^.aSlashCrossesThe"},{"#f":5}],"c-1":["ev",{"^->":"gedeonAppears.theRoomDarkensEv1.0.c-1.$r2"},"/ev",{"temp=":"$r"},{"->":".^.^.5.s"},[{"#n":"$r2"}],"\n",{"->":".^.^.^.^.gedeonsSnakeAppe1"},{"#f":5}]}],{"#f":1}],"aCoinBagAppearsO":[["^A coin bag appears on your counter.","\n","^\"Treeeat yourrrssseeelf to sooomethiiing niiiccce, yeaaa?\"","\n","^Deidamia leaves.","\n",["ev",{"^->":"gedeonAppears.aCoinBagAppearsO.0.6.$r1"},{"temp=":"$r"},"str",{"->":".^.s"},[{"#n":"$r1"}],"/str","/ev",{"*":".^.^.c-0","flg":2},{"s":["^Next",{"->":"$r","var":true},null]}],{"c-0":["ev",{"^->":"gedeonAppears.aCoinBagAppearsO.0.c-0.$r2"},"/ev",{"temp=":"$r"},{"->":".^.^.6.s"},[{"#n":"$r2"}],"\n",{"->":".^.^.^.^.mysteryAssassins"},{"#f":5}]}],{"#f":1}],"foool":[["^<em>\"Foool.\"</em>","\n",["ev",{"^->":"gedeonAppears.foool.0.2.$r1"},{"temp=":"$r"},"str",{"->":".^.s"},[{"#n":"$r1"}],"/str","/ev",{"*":".^.^.c-0","flg":2},{"s":["^Next",{"->":"$r","var":true},null]}],{"c-0":["ev",{"^->":"gedeonAppears.foool.0.c-0.$r2"},"/ev",{"temp=":"$r"},{"->":".^.^.2.s"},[{"#n":"$r2"}],"\n",{"->":".^.^.^.^.theRoomDarkensEv"},{"#f":5}]}],{"#f":1}],"aSlashCrossesThe":[["^A slash crosses the room.","\n","^The room lightens.","\n","^Gedeon looks surprised.","\n","^A red line appears across him and begins to bleed.","\n","^His top body slides to the side and falls to the ground with a thud.","\n","^A moment of silence.","\n","^Cain appears.","\n","^\"....\"","\n",["ev",{"^->":"gedeonAppears.aSlashCrossesThe.0.16.$r1"},{"temp=":"$r"},"str",{"->":".^.s"},[{"#n":"$r1"}],"/str","/ev",{"*":".^.^.c-0","flg":2},{"s":["^Next",{"->":"$r","var":true},null]}],{"c-0":["ev",{"^->":"gedeonAppears.aSlashCrossesThe.0.c-0.$r2"},"/ev",{"temp=":"$r"},{"->":".^.^.16.s"},[{"#n":"$r2"}],"\n",{"->":".^.^.^.^.kkkshhhhh1"},{"#f":5}]}],{"#f":1}],"gedeonsSnakeAppe1":["^Gedeon's Snake appears.","\n","^<strong>Abrupt Ending Unlocked: Helped another, but at what cost?</strong>","\n","end",{"#f":1}],"mysteryAssassins":[["^Mystery Assassins appear throughout the remainder of the week asking for random potions.","\n","^<em>\"Greetingssss, I require a potion that will affect my targetssss negatively.\"</em>","\n",["ev",{"^->":"gedeonAppears.mysteryAssassins.0.4.$r1"},{"temp=":"$r"},"str",{"->":".^.s"},[{"#n":"$r1"}],"/str","/ev",{"*":".^.^.c-0","flg":2},{"s":["^Correct Potion",{"->":"$r","var":true},null]}],["ev",{"^->":"gedeonAppears.mysteryAssassins.0.5.$r1"},{"temp=":"$r"},"str",{"->":".^.s"},[{"#n":"$r1"}],"/str","/ev",{"*":".^.^.c-1","flg":2},{"s":["^Incorrect Potion",{"->":"$r","var":true},null]}],{"c-0":["ev",{"^->":"gedeonAppears.mysteryAssassins.0.c-0.$r2"},"/ev",{"temp=":"$r"},{"->":".^.^.4.s"},[{"#n":"$r2"}],"\n",{"->":".^.^.^.^.thankssss"},{"#f":5}],"c-1":["ev",{"^->":"gedeonAppears.mysteryAssassins.0.c-1.$r2"},"/ev",{"temp=":"$r"},{"->":".^.^.5.s"},[{"#n":"$r2"}],"\n",{"->":".^.^.^.^.punctuatedStitch15"},{"#f":5}]}],{"#f":1}],"thankssss":["^<em>\"Thankssss.\"</em>","\n","^The Mystery Assassin leaves.<em></em>","\n","^The Assassins continue to appear.","\n","^<strong>Ending Unlocked: Menacccce to Ssssocccciety</strong>","\n","end",{"#f":1}],"punctuatedStitch15":[["^<em>\"....\"</em>","\n",["ev",{"^->":"gedeonAppears.punctuatedStitch15.0.2.$r1"},{"temp=":"$r"},"str",{"->":".^.s"},[{"#n":"$r1"}],"/str","/ev",{"*":".^.^.c-0","flg":2},{"s":["^Next",{"->":"$r","var":true},null]}],{"c-0":["ev",{"^->":"gedeonAppears.punctuatedStitch15.0.c-0.$r2"},"/ev",{"temp=":"$r"},{"->":".^.^.2.s"},[{"#n":"$r2"}],"\n",{"->":".^.^.^.^.failureIssssNotT"},{"#f":5}]}],{"#f":1}],"failureIssssNotT":["^<em>\"Failure issss not tolerated.\"</em>","\n","^A slash crosses the room.","\n","^<strong>Abrupt Ending Unlocked: Terminated. Reason: Failure to meet sssstandardssss.</strong><em></em>","\n","end",{"#f":1}],"kkkshhhhh1":[["^\"K-k-kshhhhh\"","\n",["ev",{"^->":"gedeonAppears.kkkshhhhh1.0.2.$r1"},{"temp=":"$r"},"str",{"->":".^.s"},[{"#n":"$r1"}],"/str","/ev",{"*":".^.^.c-0","flg":2},{"s":["^Next",{"->":"$r","var":true},null]}],{"c-0":["ev",{"^->":"gedeonAppears.kkkshhhhh1.0.c-0.$r2"},"/ev",{"temp=":"$r"},{"->":".^.^.2.s"},[{"#n":"$r2"}],"\n",{"->":".^.^.^.^.wellIllBe1"},{"#f":5}]}],{"#f":1}],"wellIllBe1":[["^\"Well, I'll be...\"","\n",["ev",{"^->":"gedeonAppears.wellIllBe1.0.2.$r1"},{"temp=":"$r"},"str",{"->":".^.s"},[{"#n":"$r1"}],"/str","/ev",{"*":".^.^.c-0","flg":2},{"s":["^Next",{"->":"$r","var":true},null]}],{"c-0":["ev",{"^->":"gedeonAppears.wellIllBe1.0.c-0.$r2"},"/ev",{"temp=":"$r"},{"->":".^.^.2.s"},[{"#n":"$r2"}],"\n",{"->":".^.^.^.^.hesUglierThanABu"},{"#f":5}]}],{"#f":1}],"hesUglierThanABu":[["^\"He's uglier than a burned boot. K-kshhh\"","\n",["ev",{"^->":"gedeonAppears.hesUglierThanABu.0.2.$r1"},{"temp=":"$r"},"str",{"->":".^.s"},[{"#n":"$r1"}],"/str","/ev",{"*":".^.^.c-0","flg":2},{"s":["^....",{"->":"$r","var":true},null]}],{"c-0":["ev",{"^->":"gedeonAppears.hesUglierThanABu.0.c-0.$r2"},"/ev",{"temp=":"$r"},{"->":".^.^.2.s"},[{"#n":"$r2"}],"\n",{"->":".^.^.^.^.nowDontYaGoLooki"},{"#f":5}]}],{"#f":1}],"nowDontYaGoLooki":[["^\"Now, don't ya go looking at me like that partner.\"","\n",["ev",{"^->":"gedeonAppears.nowDontYaGoLooki.0.2.$r1"},{"temp=":"$r"},"str",{"->":".^.s"},[{"#n":"$r1"}],"/str","/ev",{"*":".^.^.c-0","flg":2},{"s":["^Next",{"->":"$r","var":true},null]}],{"c-0":["ev",{"^->":"gedeonAppears.nowDontYaGoLooki.0.c-0.$r2"},"/ev",{"temp=":"$r"},{"->":".^.^.2.s"},[{"#n":"$r2"}],"\n",{"->":".^.^.^.^.imHandsomeAsCanB"},{"#f":5}]}],{"#f":1}],"imHandsomeAsCanB":[["^\"I'm handsome as can be. k-kshhh\"","\n",["ev",{"^->":"gedeonAppears.imHandsomeAsCanB.0.2.$r1"},{"temp=":"$r"},"str",{"->":".^.s"},[{"#n":"$r1"}],"/str","/ev",{"*":".^.^.c-0","flg":2},{"s":["^Next",{"->":"$r","var":true},null]}],{"c-0":["ev",{"^->":"gedeonAppears.imHandsomeAsCanB.0.c-0.$r2"},"/ev",{"temp=":"$r"},{"->":".^.^.2.s"},[{"#n":"$r2"}],"\n",{"->":".^.^.^.^.aCoinBagAppearsO1"},{"#f":5}]}],{"#f":1}],"aCoinBagAppearsO1":[["^A coin bag appears on your counter.","\n","^\"For the clean-up.\"","\n",["ev",{"^->":"gedeonAppears.aCoinBagAppearsO1.0.4.$r1"},{"temp=":"$r"},"str",{"->":".^.s"},[{"#n":"$r1"}],"/str","/ev",{"*":".^.^.c-0","flg":2},{"s":["^Next",{"->":"$r","var":true},null]}],{"c-0":["ev",{"^->":"gedeonAppears.aCoinBagAppearsO1.0.c-0.$r2"},"/ev",{"temp=":"$r"},{"->":".^.^.4.s"},[{"#n":"$r2"}],"\n",{"->":".^.^.^.^.yourCatSitsUp"},{"#f":5}]}],{"#f":1}],"yourCatSitsUp":[["^Your cat sits up.","\n","^\"Don't mind if I do.\"","\n",["ev",{"^->":"gedeonAppears.yourCatSitsUp.0.4.$r1"},{"temp=":"$r"},"str",{"->":".^.s"},[{"#n":"$r1"}],"/str","/ev",{"*":".^.^.c-0","flg":2},{"s":["^Next",{"->":"$r","var":true},null]}],{"c-0":["ev",{"^->":"gedeonAppears.yourCatSitsUp.0.c-0.$r2"},"/ev",{"temp=":"$r"},{"->":".^.^.4.s"},[{"#n":"$r2"}],"\n",{"->":".^.^.^.^.yourCatsEyesGlow"},{"#f":5}]}],{"#f":1}],"yourCatsEyesGlow":[["^Your cat's eyes glow, and both the coin bag and body disappear.","\n","^Your cat returns to sleep.","\n",["ev",{"^->":"gedeonAppears.yourCatsEyesGlow.0.4.$r1"},{"temp=":"$r"},"str",{"->":".^.s"},[{"#n":"$r1"}],"/str","/ev",{"*":".^.^.c-0","flg":2},{"s":["^Next",{"->":"$r","var":true},null]}],{"c-0":["ev",{"^->":"gedeonAppears.yourCatsEyesGlow.0.c-0.$r2"},"/ev",{"temp=":"$r"},{"->":".^.^.4.s"},[{"#n":"$r2"}],"\n",{"->":".^.^.^.^.kkshhhNowForWhat"},{"#f":5}]}],{"#f":1}],"kkshhhNowForWhat":[["^\"K-kshhh. Now for what I was really here for...\"","\n",["ev",{"^->":"gedeonAppears.kkshhhNowForWhat.0.2.$r1"},{"temp=":"$r"},"str",{"->":".^.s"},[{"#n":"$r1"}],"/str","/ev",{"*":".^.^.c-0","flg":2},{"s":["^Next",{"->":"$r","var":true},null]}],{"c-0":["ev",{"^->":"gedeonAppears.kkshhhNowForWhat.0.c-0.$r2"},"/ev",{"temp=":"$r"},{"->":".^.^.2.s"},[{"#n":"$r2"}],"\n",{"->":".^.^.^.^.mindSellingMeNot"},{"#f":5}]}],{"#f":1}],"mindSellingMeNot":[["^\"Mind selling me 'nother of the same potion?\"","\n",["ev",{"^->":"gedeonAppears.mindSellingMeNot.0.2.$r1"},{"temp=":"$r"},"str",{"->":".^.s"},[{"#n":"$r1"}],"/str","/ev",{"*":".^.^.c-0","flg":2},{"s":["^Antidote",{"->":"$r","var":true},null]}],["ev",{"^->":"gedeonAppears.mindSellingMeNot.0.3.$r1"},{"temp=":"$r"},"str",{"->":".^.s"},[{"#n":"$r1"}],"/str","/ev",{"*":".^.^.c-1","flg":2},{"s":["^6th Sense",{"->":"$r","var":true},null]}],["ev",{"^->":"gedeonAppears.mindSellingMeNot.0.4.$r1"},{"temp=":"$r"},"str",{"->":".^.s"},[{"#n":"$r1"}],"/str","/ev",{"*":".^.^.c-2","flg":2},{"s":["^Health Potion",{"->":"$r","var":true},null]}],{"c-0":["ev",{"^->":"gedeonAppears.mindSellingMeNot.0.c-0.$r2"},"/ev",{"temp=":"$r"},{"->":".^.^.2.s"},[{"#n":"$r2"}],"\n",{"->":".^.^.^.^.muchObligedKkshh2"},{"#f":5}],"c-1":["ev",{"^->":"gedeonAppears.mindSellingMeNot.0.c-1.$r2"},"/ev",{"temp=":"$r"},{"->":".^.^.3.s"},[{"#n":"$r2"}],"\n",{"->":".^.^.^.^.muchObligedKkshh3"},{"#f":5}],"c-2":["ev",{"^->":"gedeonAppears.mindSellingMeNot.0.c-2.$r2"},"/ev",{"temp=":"$r"},{"->":".^.^.4.s"},[{"#n":"$r2"}],"\n",{"->":".^.^.^.^.wellISupposeISho"},{"#f":5}]}],{"#f":1}],"muchObligedKkshh2":[["ev",{"VAR?":"antidote"},"/ev",[{"->":".^.b","c":true},{"b":["\n","^\"Much obliged. K-kshhh\"","\n",{"->":".^.^.^.4"},null]}],"nop","\n","ev",{"VAR?":"6th_sense"},"/ev",[{"->":".^.b","c":true},{"b":["\n","^\"Well, I suppose this works too. K-kshhh\"","\n",{"->":".^.^.^.10"},null]}],"nop","\n",["ev",{"^->":"gedeonAppears.muchObligedKkshh2.0.12.$r1"},{"temp=":"$r"},"str",{"->":".^.s"},[{"#n":"$r1"}],"/str","/ev",{"*":".^.^.c-0","flg":2},{"s":["^Next",{"->":"$r","var":true},null]}],{"c-0":["ev",{"^->":"gedeonAppears.muchObligedKkshh2.0.c-0.$r2"},"/ev",{"temp=":"$r"},{"->":".^.^.12.s"},[{"#n":"$r2"}],"\n",{"->":".^.^.^.^.andDontYaWorryBo"},{"#f":5}]}],{"#f":1}],"muchObligedKkshh3":[["ev",{"VAR?":"6th_sense"},"/ev",[{"->":".^.b","c":true},{"b":["\n","^\"Much obliged. K-kshhh\"","\n",{"->":".^.^.^.4"},null]}],"nop","\n","ev",{"VAR?":"antidote"},"/ev",[{"->":".^.b","c":true},{"b":["\n","^\"Well I'll be, this is better. Much obliged. K-kshhh\"","\n",{"->":".^.^.^.10"},null]}],"nop","\n",["ev",{"^->":"gedeonAppears.muchObligedKkshh3.0.12.$r1"},{"temp=":"$r"},"str",{"->":".^.s"},[{"#n":"$r1"}],"/str","/ev",{"*":".^.^.c-0","flg":2},{"s":["^Next",{"->":"$r","var":true},null]}],{"c-0":["ev",{"^->":"gedeonAppears.muchObligedKkshh3.0.c-0.$r2"},"/ev",{"temp=":"$r"},{"->":".^.^.12.s"},[{"#n":"$r2"}],"\n",{"->":".^.^.^.^.andDontYaWorryBo"},{"#f":5}]}],{"#f":1}],"wellISupposeISho":[["^\"Well, I suppose I shoulda specified. K-kshhh\"","\n",["ev",{"^->":"gedeonAppears.wellISupposeISho.0.2.$r1"},{"temp=":"$r"},"str",{"->":".^.s"},[{"#n":"$r1"}],"/str","/ev",{"*":".^.^.c-0","flg":2},{"s":["^Next",{"->":"$r","var":true},null]}],{"c-0":["ev",{"^->":"gedeonAppears.wellISupposeISho.0.c-0.$r2"},"/ev",{"temp=":"$r"},{"->":".^.^.2.s"},[{"#n":"$r2"}],"\n",{"->":".^.^.^.^.goodLuckPartner"},{"#f":5}]}],{"#f":1}],"goodLuckPartner":[["^\"Good luck, partner.\"","\n",["ev",{"^->":"gedeonAppears.goodLuckPartner.0.2.$r1"},{"temp=":"$r"},"str",{"->":".^.s"},[{"#n":"$r1"}],"/str","/ev",{"*":".^.^.c-0","flg":2},{"s":["^Next",{"->":"$r","var":true},null]}],{"c-0":["ev",{"^->":"gedeonAppears.goodLuckPartner.0.c-0.$r2"},"/ev",{"temp=":"$r"},{"->":".^.^.2.s"},[{"#n":"$r2"}],"\n",{"->":".^.^.^.^.theRoomDarkens5"},{"#f":5}]}],{"#f":1}],"andDontYaWorryBo":[["^\"And don't ya worry 'bout them slithering snakes. As long as you do good by me, I'll make sure they don't bother ya.\"","\n",["ev",{"^->":"gedeonAppears.andDontYaWorryBo.0.2.$r1"},{"temp=":"$r"},"str",{"->":".^.s"},[{"#n":"$r1"}],"/str","/ev",{"*":".^.^.c-0","flg":2},{"s":["^Next",{"->":"$r","var":true},null]}],{"c-0":["ev",{"^->":"gedeonAppears.andDontYaWorryBo.0.c-0.$r2"},"/ev",{"temp=":"$r"},{"->":".^.^.2.s"},[{"#n":"$r2"}],"\n",{"->":".^.^.^.^.seeYouRoundPartn"},{"#f":5}]}],{"#f":1}],"theRoomDarkens5":["^The room darkens.","\n","^A Mystery Assassin appears.","\n","^<em>\"You will pay for what you've done.\"</em>","\n","^A snake appears.","\n","^<strong>Abrupt Ending Unlocked: Revenge of the Assassin</strong><em></em>","\n","end",{"#f":1}],"seeYouRoundPartn":[["^\"See you 'round, partner. K-k-kshhhhh\"","\n",["ev",{"^->":"gedeonAppears.seeYouRoundPartn.0.2.$r1"},{"temp=":"$r"},"str",{"->":".^.s"},[{"#n":"$r1"}],"/str","/ev",{"*":".^.^.c-0","flg":2},{"s":["^Next",{"->":"$r","var":true},null]}],{"c-0":["ev",{"^->":"gedeonAppears.seeYouRoundPartn.0.c-0.$r2"},"/ev",{"temp=":"$r"},{"->":".^.^.2.s"},[{"#n":"$r2"}],"\n",{"->":".^.^.^.^.cainReappearsThr"},{"#f":5}]}],{"#f":1}],"cainReappearsThr":[["^Cain reappears throughout the week.","\n","^\"K-kshhh the usual please.\"","\n",["ev",{"^->":"gedeonAppears.cainReappearsThr.0.4.$r1"},{"temp=":"$r"},"str",{"->":".^.s"},[{"#n":"$r1"}],"/str","/ev",{"*":".^.^.c-0","flg":2},{"s":["^Correct Potion",{"->":"$r","var":true},null]}],["ev",{"^->":"gedeonAppears.cainReappearsThr.0.5.$r1"},{"temp=":"$r"},"str",{"->":".^.s"},[{"#n":"$r1"}],"/str","/ev",{"*":".^.^.c-1","flg":2},{"s":["^Incorrect Potion",{"->":"$r","var":true},null]}],{"c-0":["ev",{"^->":"gedeonAppears.cainReappearsThr.0.c-0.$r2"},"/ev",{"temp=":"$r"},{"->":".^.^.4.s"},[{"#n":"$r2"}],"\n",{"->":".^.^.^.^.seeYaRoundPartne"},{"#f":5}],"c-1":["ev",{"^->":"gedeonAppears.cainReappearsThr.0.c-1.$r2"},"/ev",{"temp=":"$r"},{"->":".^.^.5.s"},[{"#n":"$r2"}],"\n",{"->":".^.^.^.^.punctuatedStitch17"},{"#f":5}]}],{"#f":1}],"seeYaRoundPartne":["^\"See ya 'round partner.\"","\n","^appears until the end of the week.","\n","^<strong>Ending Unlocked: Protective Services</strong><em></em>","\n","end",{"#f":1}],"punctuatedStitch17":[["^\"....\"","\n",["ev",{"^->":"gedeonAppears.punctuatedStitch17.0.2.$r1"},{"temp=":"$r"},"str",{"->":".^.s"},[{"#n":"$r1"}],"/str","/ev",{"*":".^.^.c-0","flg":2},{"s":["^Next",{"->":"$r","var":true},null]}],{"c-0":["ev",{"^->":"gedeonAppears.punctuatedStitch17.0.c-0.$r2"},"/ev",{"temp=":"$r"},{"->":".^.^.2.s"},[{"#n":"$r2"}],"\n",{"->":".^.^.^.^.wellISupposeISho1"},{"#f":5}]}],{"#f":1}],"wellISupposeISho1":[["^\"Well, I suppose I shoulda specified. K-kshhh\"","\n","^Cain leaves and never returns.","\n",["ev",{"^->":"gedeonAppears.wellISupposeISho1.0.4.$r1"},{"temp=":"$r"},"str",{"->":".^.s"},[{"#n":"$r1"}],"/str","/ev",{"*":".^.^.c-0","flg":2},{"s":["^Next",{"->":"$r","var":true},null]}],{"c-0":["ev",{"^->":"gedeonAppears.wellISupposeISho1.0.c-0.$r2"},"/ev",{"temp=":"$r"},{"->":".^.^.4.s"},[{"#n":"$r2"}],"\n",{"->":".^.^.^.^.theRoomDarkens5"},{"#f":5}]}],{"#f":1}],"#f":1}],"global decl":["ev",false,{"VAR=":"6th_sense"},false,{"VAR=":"helpedcain"},false,{"VAR=":"antidote"},"/ev","end",null],"#f":1}],"listDefs":{}}